[[],[{"OBJECTID":169017,"Unit_Nm":"Superior Public Lands","Pub_Access":"OA","MngNm_Desc":"City Land","MngTp_Desc":"Local Government","DesTp_Desc":"Local Park","GIS_Acres":485}],[],[],[],[],[],[],[],[],[],[],[],[],[],[],[],[],[],[],[],[],[],[],[],[],[],[],[],[],[],[],[],[],[],[],[],[],[],[],[{"OBJECTID":256574,"Unit_Nm":"Church - West","Pub_Access":"OA","MngNm_Desc":"City Land","MngTp_Desc":"Local Government","DesTp_Desc":"Local Other or Unknown","GIS_Acres":122}],[],[],[],[],[],[],[],[],[],[],[],[],[],[{"OBJECTID":90698,"Unit_Nm":"City of Boulder City Parks","Pub_Access":"OA","MngNm_Desc":"City Land","MngTp_Desc":"Local Government","DesTp_Desc":"Local Park","GIS_Acres":1357}],[{"OBJECTID":90698,"Unit_Nm":"City of Boulder City Parks","Pub_Access":"OA","MngNm_Desc":"City Land","MngTp_Desc":"Local Government","DesTp_Desc":"Local Park","GIS_Acres":1357}],[{"OBJECTID":90698,"Unit_Nm":"City of Boulder City Parks","Pub_Access":"OA","MngNm_Desc":"City Land","MngTp_Desc":"Local Government","DesTp_Desc":"Local Park","GIS_Acres":1357}],[{"OBJECTID":90698,"Unit_Nm":"City of Boulder City Parks","Pub_Access":"OA","MngNm_Desc":"City Land","MngTp_Desc":"Local Government","DesTp_Desc":"Local Park","GIS_Acres":1357}],[{"OBJECTID":90698,"Unit_Nm":"City of Boulder City Parks","Pub_Access":"OA","MngNm_Desc":"City Land","MngTp_Desc":"Local Government","DesTp_Desc":"Local Park","GIS_Acres":1357}],[{"OBJECTID":90698,"Unit_Nm":"City of Boulder City Parks","Pub_Access":"OA","MngNm_Desc":"City Land","MngTp_Desc":"Local Government","DesTp_Desc":"Local Park","GIS_Acres":1357}],[{"OBJECTID":90698,"Unit_Nm":"City of Boulder City Parks","Pub_Access":"OA","MngNm_Desc":"City Land","MngTp_Desc":"Local Government","DesTp_Desc":"Local Park","GIS_Acres":1357}],[{"OBJECTID":90698,"Unit_Nm":"City of Boulder City Parks","Pub_Access":"OA","MngNm_Desc":"City Land","MngTp_Desc":"Local Government","DesTp_Desc":"Local Park","GIS_Acres":1357}],[{"OBJECTID":90698,"Unit_Nm":"City of Boulder City Parks","Pub_Access":"OA","MngNm_Desc":"City Land","MngTp_Desc":"Local Government","DesTp_Desc":"Local Park","GIS_Acres":1357}],[{"OBJECTID":90698,"Unit_Nm":"City of Boulder City Parks","Pub_Access":"OA","MngNm_Desc":"City Land","MngTp_Desc":"Local Government","DesTp_Desc":"Local Park","GIS_Acres":1357}],[{"OBJECTID":90698,"Unit_Nm":"City of Boulder City Parks","Pub_Access":"OA","MngNm_Desc":"City Land","MngTp_Desc":"Local Government","DesTp_Desc":"Local Park","GIS_Acres":1357}],[{"OBJECTID":90698,"Unit_Nm":"City of Boulder City Parks","Pub_Access":"OA","MngNm_Desc":"City Land","MngTp_Desc":"Local Government","DesTp_Desc":"Local Park","GIS_Acres":1357}],[{"OBJECTID":90698,"Unit_Nm":"City of Boulder City Parks","Pub_Access":"OA","MngNm_Desc":"City Land","MngTp_Desc":"Local Government","DesTp_Desc":"Local Park","GIS_Acres":1357}],[{"OBJECTID":90698,"Unit_Nm":"City of Boulder City Parks","Pub_Access":"OA","MngNm_Desc":"City Land","MngTp_Desc":"Local Government","DesTp_Desc":"Local Park","GIS_Acres":1357}],[{"OBJECTID":90698,"Unit_Nm":"City of Boulder City Parks","Pub_Access":"OA","MngNm_Desc":"City Land","MngTp_Desc":"Local Government","DesTp_Desc":"Local Park","GIS_Acres":1357}],[{"OBJECTID":90698,"Unit_Nm":"City of Boulder City Parks","Pub_Access":"OA","MngNm_Desc":"City Land","MngTp_Desc":"Local Government","DesTp_Desc":"Local Park","GIS_Acres":1357}],[],[],[],[],[],[],[],[],[],[],[{"OBJECTID":90698,"Unit_Nm":"City of Boulder City Parks","Pub_Access":"OA","MngNm_Desc":"City Land","MngTp_Desc":"Local Government","DesTp_Desc":"Local Park","GIS_Acres":1357}],[{"OBJECTID":90698,"Unit_Nm":"City of Boulder City Parks","Pub_Access":"OA","MngNm_Desc":"City Land","MngTp_Desc":"Local Government","DesTp_Desc":"Local Park","GIS_Acres":1357}],[{"OBJECTID":90698,"Unit_Nm":"City of Boulder City Parks","Pub_Access":"OA","MngNm_Desc":"City Land","MngTp_Desc":"Local Government","DesTp_Desc":"Local Park","GIS_Acres":1357}],[],[],[],[],[],[],[],[],[],[],[{"OBJECTID":90698,"Unit_Nm":"City of Boulder City Parks","Pub_Access":"OA","MngNm_Desc":"City Land","MngTp_Desc":"Local Government","DesTp_Desc":"Local Park","GIS_Acres":1357}],[{"OBJECTID":90698,"Unit_Nm":"City of Boulder City Parks","Pub_Access":"OA","MngNm_Desc":"City Land","MngTp_Desc":"Local Government","DesTp_Desc":"Local Park","GIS_Acres":1357}],[{"OBJECTID":90698,"Unit_Nm":"City of Boulder City Parks","Pub_Access":"OA","MngNm_Desc":"City Land","MngTp_Desc":"Local Government","DesTp_Desc":"Local Park","GIS_Acres":1357}],[{"OBJECTID":90698,"Unit_Nm":"City of Boulder City Parks","Pub_Access":"OA","MngNm_Desc":"City Land","MngTp_Desc":"Local Government","DesTp_Desc":"Local Park","GIS_Acres":1357}],[],[],[{"OBJECTID":90698,"Unit_Nm":"City of Boulder City Parks","Pub_Access":"OA","MngNm_Desc":"City Land","MngTp_Desc":"Local Government","DesTp_Desc":"Local Park","GIS_Acres":1357}],[{"OBJECTID":90698,"Unit_Nm":"City of Boulder City Parks","Pub_Access":"OA","MngNm_Desc":"City Land","MngTp_Desc":"Local Government","DesTp_Desc":"Local Park","GIS_Acres":1357}],[],[],[{"OBJECTID":90698,"Unit_Nm":"City of Boulder City Parks","Pub_Access":"OA","MngNm_Desc":"City Land","MngTp_Desc":"Local Government","DesTp_Desc":"Local Park","GIS_Acres":1357}],[],[],[],[],[],[],[],[{"OBJECTID":90698,"Unit_Nm":"City of Boulder City Parks","Pub_Access":"OA","MngNm_Desc":"City Land","MngTp_Desc":"Local Government","DesTp_Desc":"Local Park","GIS_Acres":1357}],[{"OBJECTID":90698,"Unit_Nm":"City of Boulder City Parks","Pub_Access":"OA","MngNm_Desc":"City Land","MngTp_Desc":"Local Government","DesTp_Desc":"Local Park","GIS_Acres":1357}],[],[{"OBJECTID":90698,"Unit_Nm":"City of Boulder City Parks","Pub_Access":"OA","MngNm_Desc":"City Land","MngTp_Desc":"Local Government","DesTp_Desc":"Local Park","GIS_Acres":1357}],[{"OBJECTID":90698,"Unit_Nm":"City of Boulder City Parks","Pub_Access":"OA","MngNm_Desc":"City Land","MngTp_Desc":"Local Government","DesTp_Desc":"Local Park","GIS_Acres":1357}],[],[],[],[],[],[],[],[],[],[],[],[],[],[],[],[],[],[],[],[],[],[],[],[],[],[],[],[],[],[],[],[],[],[],[],[],[],[],[],[],[],[],[],[],[],[],[],[{"OBJECTID":90698,"Unit_Nm":"City of Boulder City Parks","Pub_Access":"OA","MngNm_Desc":"City Land","MngTp_Desc":"Local Government","DesTp_Desc":"Local Park","GIS_Acres":1357}],[],[{"OBJECTID":90698,"Unit_Nm":"City of Boulder City Parks","Pub_Access":"OA","MngNm_Desc":"City Land","MngTp_Desc":"Local Government","DesTp_Desc":"Local Park","GIS_Acres":1357}],[{"OBJECTID":90698,"Unit_Nm":"City of Boulder City Parks","Pub_Access":"OA","MngNm_Desc":"City Land","MngTp_Desc":"Local Government","DesTp_Desc":"Local Park","GIS_Acres":1357}],[],[{"OBJECTID":90698,"Unit_Nm":"City of Boulder City Parks","Pub_Access":"OA","MngNm_Desc":"City Land","MngTp_Desc":"Local Government","DesTp_Desc":"Local Park","GIS_Acres":1357}],[{"OBJECTID":90698,"Unit_Nm":"City of Boulder City Parks","Pub_Access":"OA","MngNm_Desc":"City Land","MngTp_Desc":"Local Government","DesTp_Desc":"Local Park","GIS_Acres":1357}],[],[{"OBJECTID":90698,"Unit_Nm":"City of Boulder City Parks","Pub_Access":"OA","MngNm_Desc":"City Land","MngTp_Desc":"Local Government","DesTp_Desc":"Local Park","GIS_Acres":1357}],[{"OBJECTID":90698,"Unit_Nm":"City of Boulder City Parks","Pub_Access":"OA","MngNm_Desc":"City Land","MngTp_Desc":"Local Government","DesTp_Desc":"Local Park","GIS_Acres":1357}],[{"OBJECTID":90698,"Unit_Nm":"City of Boulder City Parks","Pub_Access":"OA","MngNm_Desc":"City Land","MngTp_Desc":"Local Government","DesTp_Desc":"Local Park","GIS_Acres":1357}],[{"OBJECTID":90698,"Unit_Nm":"City of Boulder City Parks","Pub_Access":"OA","MngNm_Desc":"City Land","MngTp_Desc":"Local Government","DesTp_Desc":"Local Park","GIS_Acres":1357}],[],[{"OBJECTID":90698,"Unit_Nm":"City of Boulder City Parks","Pub_Access":"OA","MngNm_Desc":"City Land","MngTp_Desc":"Local Government","DesTp_Desc":"Local Park","GIS_Acres":1357}],[],[{"OBJECTID":90698,"Unit_Nm":"City of Boulder City Parks","Pub_Access":"OA","MngNm_Desc":"City Land","MngTp_Desc":"Local Government","DesTp_Desc":"Local Park","GIS_Acres":1357}],[{"OBJECTID":90698,"Unit_Nm":"City of Boulder City Parks","Pub_Access":"OA","MngNm_Desc":"City Land","MngTp_Desc":"Local Government","DesTp_Desc":"Local Park","GIS_Acres":1357}],[],[{"OBJECTID":90698,"Unit_Nm":"City of Boulder City Parks","Pub_Access":"OA","MngNm_Desc":"City Land","MngTp_Desc":"Local Government","DesTp_Desc":"Local Park","GIS_Acres":1357}],[],[],[{"OBJECTID":90698,"Unit_Nm":"City of Boulder City Parks","Pub_Access":"OA","MngNm_Desc":"City Land","MngTp_Desc":"Local Government","DesTp_Desc":"Local Park","GIS_Acres":1357}],[],[],[],[],[],[],[],[],[],[],[],[],[],[],[],[],[],[],[{"OBJECTID":17978,"Unit_Nm":"Burke I","Pub_Access":"OA","MngNm_Desc":"City Land","MngTp_Desc":"Local Government","DesTp_Desc":"Local Other or Unknown","GIS_Acres":88}],[],[],[],[],[],[],[],[{"OBJECTID":90698,"Unit_Nm":"City of Boulder City Parks","Pub_Access":"OA","MngNm_Desc":"City Land","MngTp_Desc":"Local Government","DesTp_Desc":"Local Park","GIS_Acres":1357}],[],[],[],[],[],[],[],[],[{"OBJECTID":17978,"Unit_Nm":"Burke I","Pub_Access":"OA","MngNm_Desc":"City Land","MngTp_Desc":"Local Government","DesTp_Desc":"Local Other or Unknown","GIS_Acres":88}],[],[],[],[],[],[],[],[],[],[],[],[],[],[],[],[],[],[],[],[],[],[],[{"OBJECTID":90698,"Unit_Nm":"City of Boulder City Parks","Pub_Access":"OA","MngNm_Desc":"City Land","MngTp_Desc":"Local Government","DesTp_Desc":"Local Park","GIS_Acres":1357}],[{"OBJECTID":90698,"Unit_Nm":"City of Boulder City Parks","Pub_Access":"OA","MngNm_Desc":"City Land","MngTp_Desc":"Local Government","DesTp_Desc":"Local Park","GIS_Acres":1357}],[{"OBJECTID":90698,"Unit_Nm":"City of Boulder City Parks","Pub_Access":"OA","MngNm_Desc":"City Land","MngTp_Desc":"Local Government","DesTp_Desc":"Local Park","GIS_Acres":1357}],[{"OBJECTID":90698,"Unit_Nm":"City of Boulder City Parks","Pub_Access":"OA","MngNm_Desc":"City Land","MngTp_Desc":"Local Government","DesTp_Desc":"Local Park","GIS_Acres":1357}],[{"OBJECTID":90698,"Unit_Nm":"City of Boulder City Parks","Pub_Access":"OA","MngNm_Desc":"City Land","MngTp_Desc":"Local Government","DesTp_Desc":"Local Park","GIS_Acres":1357}],[],[],[{"OBJECTID":90698,"Unit_Nm":"City of Boulder City Parks","Pub_Access":"OA","MngNm_Desc":"City Land","MngTp_Desc":"Local Government","DesTp_Desc":"Local Park","GIS_Acres":1357}],[{"OBJECTID":90698,"Unit_Nm":"City of Boulder City Parks","Pub_Access":"OA","MngNm_Desc":"City Land","MngTp_Desc":"Local Government","DesTp_Desc":"Local Park","GIS_Acres":1357}],[{"OBJECTID":90698,"Unit_Nm":"City of Boulder City Parks","Pub_Access":"OA","MngNm_Desc":"City Land","MngTp_Desc":"Local Government","DesTp_Desc":"Local Park","GIS_Acres":1357}],[{"OBJECTID":90698,"Unit_Nm":"City of Boulder City Parks","Pub_Access":"OA","MngNm_Desc":"City Land","MngTp_Desc":"Local Government","DesTp_Desc":"Local Park","GIS_Acres":1357}],[],[],[],[],[{"OBJECTID":90698,"Unit_Nm":"City of Boulder City Parks","Pub_Access":"OA","MngNm_Desc":"City Land","MngTp_Desc":"Local Government","DesTp_Desc":"Local Park","GIS_Acres":1357}],[{"OBJECTID":90698,"Unit_Nm":"City of Boulder City Parks","Pub_Access":"OA","MngNm_Desc":"City Land","MngTp_Desc":"Local Government","DesTp_Desc":"Local Park","GIS_Acres":1357}],[{"OBJECTID":90698,"Unit_Nm":"City of Boulder City Parks","Pub_Access":"OA","MngNm_Desc":"City Land","MngTp_Desc":"Local Government","DesTp_Desc":"Local Park","GIS_Acres":1357}],[{"OBJECTID":90698,"Unit_Nm":"City of Boulder City Parks","Pub_Access":"OA","MngNm_Desc":"City Land","MngTp_Desc":"Local Government","DesTp_Desc":"Local Park","GIS_Acres":1357}],[{"OBJECTID":90698,"Unit_Nm":"City of Boulder City Parks","Pub_Access":"OA","MngNm_Desc":"City Land","MngTp_Desc":"Local Government","DesTp_Desc":"Local Park","GIS_Acres":1357}],[{"OBJECTID":90698,"Unit_Nm":"City of Boulder City Parks","Pub_Access":"OA","MngNm_Desc":"City Land","MngTp_Desc":"Local Government","DesTp_Desc":"Local Park","GIS_Acres":1357}],[{"OBJECTID":90698,"Unit_Nm":"City of Boulder City Parks","Pub_Access":"OA","MngNm_Desc":"City Land","MngTp_Desc":"Local Government","DesTp_Desc":"Local Park","GIS_Acres":1357}],[{"OBJECTID":90698,"Unit_Nm":"City of Boulder City Parks","Pub_Access":"OA","MngNm_Desc":"City Land","MngTp_Desc":"Local Government","DesTp_Desc":"Local Park","GIS_Acres":1357}],[{"OBJECTID":90698,"Unit_Nm":"City of Boulder City Parks","Pub_Access":"OA","MngNm_Desc":"City Land","MngTp_Desc":"Local Government","DesTp_Desc":"Local Park","GIS_Acres":1357}],[{"OBJECTID":90698,"Unit_Nm":"City of Boulder City Parks","Pub_Access":"OA","MngNm_Desc":"City Land","MngTp_Desc":"Local Government","DesTp_Desc":"Local Park","GIS_Acres":1357}],[{"OBJECTID":90698,"Unit_Nm":"City of Boulder City Parks","Pub_Access":"OA","MngNm_Desc":"City Land","MngTp_Desc":"Local Government","DesTp_Desc":"Local Park","GIS_Acres":1357}],[{"OBJECTID":90698,"Unit_Nm":"City of Boulder City Parks","Pub_Access":"OA","MngNm_Desc":"City Land","MngTp_Desc":"Local Government","DesTp_Desc":"Local Park","GIS_Acres":1357}],[{"OBJECTID":90698,"Unit_Nm":"City of Boulder City Parks","Pub_Access":"OA","MngNm_Desc":"City Land","MngTp_Desc":"Local Government","DesTp_Desc":"Local Park","GIS_Acres":1357}],[{"OBJECTID":90698,"Unit_Nm":"City of Boulder City Parks","Pub_Access":"OA","MngNm_Desc":"City Land","MngTp_Desc":"Local Government","DesTp_Desc":"Local Park","GIS_Acres":1357}],[{"OBJECTID":90698,"Unit_Nm":"City of Boulder City Parks","Pub_Access":"OA","MngNm_Desc":"City Land","MngTp_Desc":"Local Government","DesTp_Desc":"Local Park","GIS_Acres":1357}],[{"OBJECTID":90698,"Unit_Nm":"City of Boulder City Parks","Pub_Access":"OA","MngNm_Desc":"City Land","MngTp_Desc":"Local Government","DesTp_Desc":"Local Park","GIS_Acres":1357}],[{"OBJECTID":90698,"Unit_Nm":"City of Boulder City Parks","Pub_Access":"OA","MngNm_Desc":"City Land","MngTp_Desc":"Local Government","DesTp_Desc":"Local Park","GIS_Acres":1357}],[{"OBJECTID":90698,"Unit_Nm":"City of Boulder City Parks","Pub_Access":"OA","MngNm_Desc":"City Land","MngTp_Desc":"Local Government","DesTp_Desc":"Local Park","GIS_Acres":1357}],[{"OBJECTID":90698,"Unit_Nm":"City of Boulder City Parks","Pub_Access":"OA","MngNm_Desc":"City Land","MngTp_Desc":"Local Government","DesTp_Desc":"Local Park","GIS_Acres":1357}],[{"OBJECTID":90698,"Unit_Nm":"City of Boulder City Parks","Pub_Access":"OA","MngNm_Desc":"City Land","MngTp_Desc":"Local Government","DesTp_Desc":"Local Park","GIS_Acres":1357}],[{"OBJECTID":90698,"Unit_Nm":"City of Boulder City Parks","Pub_Access":"OA","MngNm_Desc":"City Land","MngTp_Desc":"Local Government","DesTp_Desc":"Local Park","GIS_Acres":1357}],[{"OBJECTID":90698,"Unit_Nm":"City of Boulder City Parks","Pub_Access":"OA","MngNm_Desc":"City Land","MngTp_Desc":"Local Government","DesTp_Desc":"Local Park","GIS_Acres":1357}],[{"OBJECTID":90698,"Unit_Nm":"City of Boulder City Parks","Pub_Access":"OA","MngNm_Desc":"City Land","MngTp_Desc":"Local Government","DesTp_Desc":"Local Park","GIS_Acres":1357}],[{"OBJECTID":90698,"Unit_Nm":"City of Boulder City Parks","Pub_Access":"OA","MngNm_Desc":"City Land","MngTp_Desc":"Local Government","DesTp_Desc":"Local Park","GIS_Acres":1357}],[{"OBJECTID":90698,"Unit_Nm":"City of Boulder City Parks","Pub_Access":"OA","MngNm_Desc":"City Land","MngTp_Desc":"Local Government","DesTp_Desc":"Local Park","GIS_Acres":1357}],[{"OBJECTID":90698,"Unit_Nm":"City of Boulder City Parks","Pub_Access":"OA","MngNm_Desc":"City Land","MngTp_Desc":"Local Government","DesTp_Desc":"Local Park","GIS_Acres":1357}],[{"OBJECTID":90698,"Unit_Nm":"City of Boulder City Parks","Pub_Access":"OA","MngNm_Desc":"City Land","MngTp_Desc":"Local Government","DesTp_Desc":"Local Park","GIS_Acres":1357}],[{"OBJECTID":90698,"Unit_Nm":"City of Boulder City Parks","Pub_Access":"OA","MngNm_Desc":"City Land","MngTp_Desc":"Local Government","DesTp_Desc":"Local Park","GIS_Acres":1357}],[{"OBJECTID":90698,"Unit_Nm":"City of Boulder City Parks","Pub_Access":"OA","MngNm_Desc":"City Land","MngTp_Desc":"Local Government","DesTp_Desc":"Local Park","GIS_Acres":1357}],[{"OBJECTID":90698,"Unit_Nm":"City of Boulder City Parks","Pub_Access":"OA","MngNm_Desc":"City Land","MngTp_Desc":"Local Government","DesTp_Desc":"Local Park","GIS_Acres":1357}],[{"OBJECTID":90698,"Unit_Nm":"City of Boulder City Parks","Pub_Access":"OA","MngNm_Desc":"City Land","MngTp_Desc":"Local Government","DesTp_Desc":"Local Park","GIS_Acres":1357}],[{"OBJECTID":90698,"Unit_Nm":"City of Boulder City Parks","Pub_Access":"OA","MngNm_Desc":"City Land","MngTp_Desc":"Local Government","DesTp_Desc":"Local Park","GIS_Acres":1357}],[{"OBJECTID":90698,"Unit_Nm":"City of Boulder City Parks","Pub_Access":"OA","MngNm_Desc":"City Land","MngTp_Desc":"Local Government","DesTp_Desc":"Local Park","GIS_Acres":1357}],[{"OBJECTID":90698,"Unit_Nm":"City of Boulder City Parks","Pub_Access":"OA","MngNm_Desc":"City Land","MngTp_Desc":"Local Government","DesTp_Desc":"Local Park","GIS_Acres":1357}],[{"OBJECTID":90698,"Unit_Nm":"City of Boulder City Parks","Pub_Access":"OA","MngNm_Desc":"City Land","MngTp_Desc":"Local Government","DesTp_Desc":"Local Park","GIS_Acres":1357}],[{"OBJECTID":90698,"Unit_Nm":"City of Boulder City Parks","Pub_Access":"OA","MngNm_Desc":"City Land","MngTp_Desc":"Local Government","DesTp_Desc":"Local Park","GIS_Acres":1357}],[{"OBJECTID":90698,"Unit_Nm":"City of Boulder City Parks","Pub_Access":"OA","MngNm_Desc":"City Land","MngTp_Desc":"Local Government","DesTp_Desc":"Local Park","GIS_Acres":1357}],[{"OBJECTID":90698,"Unit_Nm":"City of Boulder City Parks","Pub_Access":"OA","MngNm_Desc":"City Land","MngTp_Desc":"Local Government","DesTp_Desc":"Local Park","GIS_Acres":1357}],[],[],[],[],[],[],[],[],[],[],[],[],[{"OBJECTID":90698,"Unit_Nm":"City of Boulder City Parks","Pub_Access":"OA","MngNm_Desc":"City Land","MngTp_Desc":"Local Government","DesTp_Desc":"Local Park","GIS_Acres":1357}],[],[],[],[],[],[],[{"OBJECTID":90698,"Unit_Nm":"City of Boulder City Parks","Pub_Access":"OA","MngNm_Desc":"City Land","MngTp_Desc":"Local Government","DesTp_Desc":"Local Park","GIS_Acres":1357}],[{"OBJECTID":90698,"Unit_Nm":"City of Boulder City Parks","Pub_Access":"OA","MngNm_Desc":"City Land","MngTp_Desc":"Local Government","DesTp_Desc":"Local Park","GIS_Acres":1357}],[{"OBJECTID":90698,"Unit_Nm":"City of Boulder City Parks","Pub_Access":"OA","MngNm_Desc":"City Land","MngTp_Desc":"Local Government","DesTp_Desc":"Local Park","GIS_Acres":1357}],[{"OBJECTID":90698,"Unit_Nm":"City of Boulder City Parks","Pub_Access":"OA","MngNm_Desc":"City Land","MngTp_Desc":"Local Government","DesTp_Desc":"Local Park","GIS_Acres":1357}],[],[],[{"OBJECTID":90698,"Unit_Nm":"City of Boulder City Parks","Pub_Access":"OA","MngNm_Desc":"City Land","MngTp_Desc":"Local Government","DesTp_Desc":"Local Park","GIS_Acres":1357}],[{"OBJECTID":90698,"Unit_Nm":"City of Boulder City Parks","Pub_Access":"OA","MngNm_Desc":"City Land","MngTp_Desc":"Local Government","DesTp_Desc":"Local Park","GIS_Acres":1357}],[{"OBJECTID":90698,"Unit_Nm":"City of Boulder City Parks","Pub_Access":"OA","MngNm_Desc":"City Land","MngTp_Desc":"Local Government","DesTp_Desc":"Local Park","GIS_Acres":1357}],[],[],[{"OBJECTID":90698,"Unit_Nm":"City of Boulder City Parks","Pub_Access":"OA","MngNm_Desc":"City Land","MngTp_Desc":"Local Government","DesTp_Desc":"Local Park","GIS_Acres":1357}],[{"OBJECTID":90698,"Unit_Nm":"City of Boulder City Parks","Pub_Access":"OA","MngNm_Desc":"City Land","MngTp_Desc":"Local Government","DesTp_Desc":"Local Park","GIS_Acres":1357}],[{"OBJECTID":90698,"Unit_Nm":"City of Boulder City Parks","Pub_Access":"OA","MngNm_Desc":"City Land","MngTp_Desc":"Local Government","DesTp_Desc":"Local Park","GIS_Acres":1357}],[{"OBJECTID":90698,"Unit_Nm":"City of Boulder City Parks","Pub_Access":"OA","MngNm_Desc":"City Land","MngTp_Desc":"Local Government","DesTp_Desc":"Local Park","GIS_Acres":1357}],[],[{"OBJECTID":90698,"Unit_Nm":"City of Boulder City Parks","Pub_Access":"OA","MngNm_Desc":"City Land","MngTp_Desc":"Local Government","DesTp_Desc":"Local Park","GIS_Acres":1357}],[{"OBJECTID":90698,"Unit_Nm":"City of Boulder City Parks","Pub_Access":"OA","MngNm_Desc":"City Land","MngTp_Desc":"Local Government","DesTp_Desc":"Local Park","GIS_Acres":1357}],[{"OBJECTID":90698,"Unit_Nm":"City of Boulder City Parks","Pub_Access":"OA","MngNm_Desc":"City Land","MngTp_Desc":"Local Government","DesTp_Desc":"Local Park","GIS_Acres":1357}],[{"OBJECTID":90698,"Unit_Nm":"City of Boulder City Parks","Pub_Access":"OA","MngNm_Desc":"City Land","MngTp_Desc":"Local Government","DesTp_Desc":"Local Park","GIS_Acres":1357}],[{"OBJECTID":90698,"Unit_Nm":"City of Boulder City Parks","Pub_Access":"OA","MngNm_Desc":"City Land","MngTp_Desc":"Local Government","DesTp_Desc":"Local Park","GIS_Acres":1357}],[{"OBJECTID":90698,"Unit_Nm":"City of Boulder City Parks","Pub_Access":"OA","MngNm_Desc":"City Land","MngTp_Desc":"Local Government","DesTp_Desc":"Local Park","GIS_Acres":1357}],[{"OBJECTID":90698,"Unit_Nm":"City of Boulder City Parks","Pub_Access":"OA","MngNm_Desc":"City Land","MngTp_Desc":"Local Government","DesTp_Desc":"Local Park","GIS_Acres":1357}],[{"OBJECTID":90698,"Unit_Nm":"City of Boulder City Parks","Pub_Access":"OA","MngNm_Desc":"City Land","MngTp_Desc":"Local Government","DesTp_Desc":"Local Park","GIS_Acres":1357}],[{"OBJECTID":90698,"Unit_Nm":"City of Boulder City Parks","Pub_Access":"OA","MngNm_Desc":"City Land","MngTp_Desc":"Local Government","DesTp_Desc":"Local Park","GIS_Acres":1357}],[],[],[],[],[],[],[],[],[],[],[],[],[{"OBJECTID":90698,"Unit_Nm":"City of Boulder City Parks","Pub_Access":"OA","MngNm_Desc":"City Land","MngTp_Desc":"Local Government","DesTp_Desc":"Local Park","GIS_Acres":1357}],[{"OBJECTID":90698,"Unit_Nm":"City of Boulder City Parks","Pub_Access":"OA","MngNm_Desc":"City Land","MngTp_Desc":"Local Government","DesTp_Desc":"Local Park","GIS_Acres":1357}],[],[{"OBJECTID":90698,"Unit_Nm":"City of Boulder City Parks","Pub_Access":"OA","MngNm_Desc":"City Land","MngTp_Desc":"Local Government","DesTp_Desc":"Local Park","GIS_Acres":1357}],[{"OBJECTID":90698,"Unit_Nm":"City of Boulder City Parks","Pub_Access":"OA","MngNm_Desc":"City Land","MngTp_Desc":"Local Government","DesTp_Desc":"Local Park","GIS_Acres":1357}],[],[{"OBJECTID":274574,"Unit_Nm":"Gebhard","Pub_Access":"OA","MngNm_Desc":"City Land","MngTp_Desc":"Local Government","DesTp_Desc":"Local Other or Unknown","GIS_Acres":104}],[],[],[{"OBJECTID":17978,"Unit_Nm":"Burke I","Pub_Access":"OA","MngNm_Desc":"City Land","MngTp_Desc":"Local Government","DesTp_Desc":"Local Other or Unknown","GIS_Acres":88}],[{"OBJECTID":17978,"Unit_Nm":"Burke I","Pub_Access":"OA","MngNm_Desc":"City Land","MngTp_Desc":"Local Government","DesTp_Desc":"Local Other or Unknown","GIS_Acres":88}],[],[],[],[],[],[],[],[],[],[],[],[],[],[],[],[],[],[],[],[],[],[],[],[],[],[],[],[],[],[],[],[],[],[],[],[],[],[],[],[],[],[],[],[],[],[],[],[],[],[],[],[],[],[],[],[],[],[],[],[],[],[],[],[],[],[],[],[],[],[],[],[{"OBJECTID":284173,"Unit_Nm":"Burke II","Pub_Access":"OA","MngNm_Desc":"City Land","MngTp_Desc":"Local Government","DesTp_Desc":"Local Other or Unknown","GIS_Acres":68}],[],[],[],[{"OBJECTID":284173,"Unit_Nm":"Burke II","Pub_Access":"OA","MngNm_Desc":"City Land","MngTp_Desc":"Local Government","DesTp_Desc":"Local Other or Unknown","GIS_Acres":68}],[],[],[],[],[{"OBJECTID":90698,"Unit_Nm":"City of Boulder City Parks","Pub_Access":"OA","MngNm_Desc":"City Land","MngTp_Desc":"Local Government","DesTp_Desc":"Local Park","GIS_Acres":1357}],[{"OBJECTID":90698,"Unit_Nm":"City of Boulder City Parks","Pub_Access":"OA","MngNm_Desc":"City Land","MngTp_Desc":"Local Government","DesTp_Desc":"Local Park","GIS_Acres":1357}],[],[],[],[],[],[],[],[],[],[],[],[],[],[],[],[],[],[],[],[{"OBJECTID":139932,"Unit_Nm":"Park East","Pub_Access":"OA","MngNm_Desc":"City Land","MngTp_Desc":"Local Government","DesTp_Desc":"Local Park","GIS_Acres":6}],[],[],[],[{"OBJECTID":90698,"Unit_Nm":"City of Boulder City Parks","Pub_Access":"OA","MngNm_Desc":"City Land","MngTp_Desc":"Local Government","DesTp_Desc":"Local Park","GIS_Acres":1357}],[],[],[],[],[],[],[],[{"OBJECTID":35222,"Unit_Nm":"Hatch-quinby-phipps","Pub_Access":"OA","MngNm_Desc":"City Land","MngTp_Desc":"Local Government","DesTp_Desc":"Local Other or Unknown","GIS_Acres":8}],[],[],[{"OBJECTID":90698,"Unit_Nm":"City of Boulder City Parks","Pub_Access":"OA","MngNm_Desc":"City Land","MngTp_Desc":"Local Government","DesTp_Desc":"Local Park","GIS_Acres":1357}],[{"OBJECTID":90698,"Unit_Nm":"City of Boulder City Parks","Pub_Access":"OA","MngNm_Desc":"City Land","MngTp_Desc":"Local Government","DesTp_Desc":"Local Park","GIS_Acres":1357}],[{"OBJECTID":90698,"Unit_Nm":"City of Boulder City Parks","Pub_Access":"OA","MngNm_Desc":"City Land","MngTp_Desc":"Local Government","DesTp_Desc":"Local Park","GIS_Acres":1357}],[],[],[],[],[],[],[],[],[],[],[],[],[],[],[],[],[],[],[{"OBJECTID":90698,"Unit_Nm":"City of Boulder City Parks","Pub_Access":"OA","MngNm_Desc":"City Land","MngTp_Desc":"Local Government","DesTp_Desc":"Local Park","GIS_Acres":1357}],[],[],[],[],[],[],[],[],[],[],[],[],[],[],[],[],[],[],[],[],[],[],[],[],[],[],[],[],[],[],[],[],[],[],[],[],[],[],[],[],[],[],[],[],[],[],[],[],[],[],[],[],[],[],[],[],[],[],[],[],[],[],[],[],[],[],[],[],[],[],[],[],[],[],[],[],[],[],[],[],[{"OBJECTID":38745,"Unit_Nm":"Valmont Bike Park","Pub_Access":"OA","MngNm_Desc":"City Land","MngTp_Desc":"Local Government","DesTp_Desc":"Local Recreation Area","GIS_Acres":40}],[],[],[],[],[],[],[],[],[],[],[],[],[],[],[{"OBJECTID":90698,"Unit_Nm":"City of Boulder City Parks","Pub_Access":"OA","MngNm_Desc":"City Land","MngTp_Desc":"Local Government","DesTp_Desc":"Local Park","GIS_Acres":1357}],[],[{"OBJECTID":90698,"Unit_Nm":"City of Boulder City Parks","Pub_Access":"OA","MngNm_Desc":"City Land","MngTp_Desc":"Local Government","DesTp_Desc":"Local Park","GIS_Acres":1357}],[{"OBJECTID":90698,"Unit_Nm":"City of Boulder City Parks","Pub_Access":"OA","MngNm_Desc":"City Land","MngTp_Desc":"Local Government","DesTp_Desc":"Local Park","GIS_Acres":1357}],[{"OBJECTID":90698,"Unit_Nm":"City of Boulder City Parks","Pub_Access":"OA","MngNm_Desc":"City Land","MngTp_Desc":"Local Government","DesTp_Desc":"Local Park","GIS_Acres":1357}],[{"OBJECTID":90698,"Unit_Nm":"City of Boulder City Parks","Pub_Access":"OA","MngNm_Desc":"City Land","MngTp_Desc":"Local Government","DesTp_Desc":"Local Park","GIS_Acres":1357}],[{"OBJECTID":90698,"Unit_Nm":"City of Boulder City Parks","Pub_Access":"OA","MngNm_Desc":"City Land","MngTp_Desc":"Local Government","DesTp_Desc":"Local Park","GIS_Acres":1357}],[],[],[],[{"OBJECTID":90698,"Unit_Nm":"City of Boulder City Parks","Pub_Access":"OA","MngNm_Desc":"City Land","MngTp_Desc":"Local Government","DesTp_Desc":"Local Park","GIS_Acres":1357}],[{"OBJECTID":90698,"Unit_Nm":"City of Boulder City Parks","Pub_Access":"OA","MngNm_Desc":"City Land","MngTp_Desc":"Local Government","DesTp_Desc":"Local Park","GIS_Acres":1357}],[{"OBJECTID":90698,"Unit_Nm":"City of Boulder City Parks","Pub_Access":"OA","MngNm_Desc":"City Land","MngTp_Desc":"Local Government","DesTp_Desc":"Local Park","GIS_Acres":1357}],[{"OBJECTID":90698,"Unit_Nm":"City of Boulder City Parks","Pub_Access":"OA","MngNm_Desc":"City Land","MngTp_Desc":"Local Government","DesTp_Desc":"Local Park","GIS_Acres":1357}],[{"OBJECTID":90698,"Unit_Nm":"City of Boulder City Parks","Pub_Access":"OA","MngNm_Desc":"City Land","MngTp_Desc":"Local Government","DesTp_Desc":"Local Park","GIS_Acres":1357}],[{"OBJECTID":90698,"Unit_Nm":"City of Boulder City Parks","Pub_Access":"OA","MngNm_Desc":"City Land","MngTp_Desc":"Local Government","DesTp_Desc":"Local Park","GIS_Acres":1357}],[{"OBJECTID":90698,"Unit_Nm":"City of Boulder City Parks","Pub_Access":"OA","MngNm_Desc":"City Land","MngTp_Desc":"Local Government","DesTp_Desc":"Local Park","GIS_Acres":1357}],[{"OBJECTID":90698,"Unit_Nm":"City of Boulder City Parks","Pub_Access":"OA","MngNm_Desc":"City Land","MngTp_Desc":"Local Government","DesTp_Desc":"Local Park","GIS_Acres":1357}],[],[],[],[],[],[],[],[],[],[],[],[],[],[],[],[],[],[],[],[],[],[],[],[],[],[],[],[],[],[],[{"OBJECTID":90698,"Unit_Nm":"City of Boulder City Parks","Pub_Access":"OA","MngNm_Desc":"City Land","MngTp_Desc":"Local Government","DesTp_Desc":"Local Park","GIS_Acres":1357}],[{"OBJECTID":90698,"Unit_Nm":"City of Boulder City Parks","Pub_Access":"OA","MngNm_Desc":"City Land","MngTp_Desc":"Local Government","DesTp_Desc":"Local Park","GIS_Acres":1357}],[{"OBJECTID":90698,"Unit_Nm":"City of Boulder City Parks","Pub_Access":"OA","MngNm_Desc":"City Land","MngTp_Desc":"Local Government","DesTp_Desc":"Local Park","GIS_Acres":1357}],[{"OBJECTID":90698,"Unit_Nm":"City of Boulder City Parks","Pub_Access":"OA","MngNm_Desc":"City Land","MngTp_Desc":"Local Government","DesTp_Desc":"Local Park","GIS_Acres":1357}],[{"OBJECTID":90698,"Unit_Nm":"City of Boulder City Parks","Pub_Access":"OA","MngNm_Desc":"City Land","MngTp_Desc":"Local Government","DesTp_Desc":"Local Park","GIS_Acres":1357}],[{"OBJECTID":90698,"Unit_Nm":"City of Boulder City Parks","Pub_Access":"OA","MngNm_Desc":"City Land","MngTp_Desc":"Local Government","DesTp_Desc":"Local Park","GIS_Acres":1357}],[],[],[],[],[],[],[{"OBJECTID":90698,"Unit_Nm":"City of Boulder City Parks","Pub_Access":"OA","MngNm_Desc":"City Land","MngTp_Desc":"Local Government","DesTp_Desc":"Local Park","GIS_Acres":1357}],[],[{"OBJECTID":90698,"Unit_Nm":"City of Boulder City Parks","Pub_Access":"OA","MngNm_Desc":"City Land","MngTp_Desc":"Local Government","DesTp_Desc":"Local Park","GIS_Acres":1357}],[],[],[],[],[],[],[],[],[],[],[],[],[],[],[],[],[{"OBJECTID":80050,"Unit_Nm":"City of Boulder City Land - General","Pub_Access":"OA","MngNm_Desc":"City Land","MngTp_Desc":"Local Government","DesTp_Desc":"Local Other or Unknown","GIS_Acres":23}],[],[{"OBJECTID":90698,"Unit_Nm":"City of Boulder City Parks","Pub_Access":"OA","MngNm_Desc":"City Land","MngTp_Desc":"Local Government","DesTp_Desc":"Local Park","GIS_Acres":1357}],[{"OBJECTID":90698,"Unit_Nm":"City of Boulder City Parks","Pub_Access":"OA","MngNm_Desc":"City Land","MngTp_Desc":"Local Government","DesTp_Desc":"Local Park","GIS_Acres":1357}],[{"OBJECTID":90698,"Unit_Nm":"City of Boulder City Parks","Pub_Access":"OA","MngNm_Desc":"City Land","MngTp_Desc":"Local Government","DesTp_Desc":"Local Park","GIS_Acres":1357}],[{"OBJECTID":90698,"Unit_Nm":"City of Boulder City Parks","Pub_Access":"OA","MngNm_Desc":"City Land","MngTp_Desc":"Local Government","DesTp_Desc":"Local Park","GIS_Acres":1357}],[],[],[],[],[],[],[{"OBJECTID":80050,"Unit_Nm":"City of Boulder City Land - General","Pub_Access":"OA","MngNm_Desc":"City Land","MngTp_Desc":"Local Government","DesTp_Desc":"Local Other or Unknown","GIS_Acres":23}],[],[],[],[],[],[],[],[],[],[],[],[],[{"OBJECTID":90698,"Unit_Nm":"City of Boulder City Parks","Pub_Access":"OA","MngNm_Desc":"City Land","MngTp_Desc":"Local Government","DesTp_Desc":"Local Park","GIS_Acres":1357}],[{"OBJECTID":90698,"Unit_Nm":"City of Boulder City Parks","Pub_Access":"OA","MngNm_Desc":"City Land","MngTp_Desc":"Local Government","DesTp_Desc":"Local Park","GIS_Acres":1357}],[{"OBJECTID":90698,"Unit_Nm":"City of Boulder City Parks","Pub_Access":"OA","MngNm_Desc":"City Land","MngTp_Desc":"Local Government","DesTp_Desc":"Local Park","GIS_Acres":1357}],[{"OBJECTID":90698,"Unit_Nm":"City of Boulder City Parks","Pub_Access":"OA","MngNm_Desc":"City Land","MngTp_Desc":"Local Government","DesTp_Desc":"Local Park","GIS_Acres":1357}],[],[],[],[],[],[],[],[],[],[],[],[],[],[],[],[],[],[],[],[],[],[],[],[],[],[],[],[],[],[],[],[],[],[],[],[],[],[],[],[],[],[],[],[],[],[{"OBJECTID":90698,"Unit_Nm":"City of Boulder City Parks","Pub_Access":"OA","MngNm_Desc":"City Land","MngTp_Desc":"Local Government","DesTp_Desc":"Local Park","GIS_Acres":1357}],[{"OBJECTID":90698,"Unit_Nm":"City of Boulder City Parks","Pub_Access":"OA","MngNm_Desc":"City Land","MngTp_Desc":"Local Government","DesTp_Desc":"Local Park","GIS_Acres":1357}],[{"OBJECTID":90698,"Unit_Nm":"City of Boulder City Parks","Pub_Access":"OA","MngNm_Desc":"City Land","MngTp_Desc":"Local Government","DesTp_Desc":"Local Park","GIS_Acres":1357}],[],[{"OBJECTID":90698,"Unit_Nm":"City of Boulder City Parks","Pub_Access":"OA","MngNm_Desc":"City Land","MngTp_Desc":"Local Government","DesTp_Desc":"Local Park","GIS_Acres":1357}],[{"OBJECTID":90698,"Unit_Nm":"City of Boulder City Parks","Pub_Access":"OA","MngNm_Desc":"City Land","MngTp_Desc":"Local Government","DesTp_Desc":"Local Park","GIS_Acres":1357}],[{"OBJECTID":90698,"Unit_Nm":"City of Boulder City Parks","Pub_Access":"OA","MngNm_Desc":"City Land","MngTp_Desc":"Local Government","DesTp_Desc":"Local Park","GIS_Acres":1357}],[],[],[],[],[],[{"OBJECTID":90698,"Unit_Nm":"City of Boulder City Parks","Pub_Access":"OA","MngNm_Desc":"City Land","MngTp_Desc":"Local Government","DesTp_Desc":"Local Park","GIS_Acres":1357}],[],[],[],[],[],[],[{"OBJECTID":90698,"Unit_Nm":"City of Boulder City Parks","Pub_Access":"OA","MngNm_Desc":"City Land","MngTp_Desc":"Local Government","DesTp_Desc":"Local Park","GIS_Acres":1357}],[],[],[{"OBJECTID":90698,"Unit_Nm":"City of Boulder City Parks","Pub_Access":"OA","MngNm_Desc":"City Land","MngTp_Desc":"Local Government","DesTp_Desc":"Local Park","GIS_Acres":1357}],[{"OBJECTID":90698,"Unit_Nm":"City of Boulder City Parks","Pub_Access":"OA","MngNm_Desc":"City Land","MngTp_Desc":"Local Government","DesTp_Desc":"Local Park","GIS_Acres":1357}],[{"OBJECTID":90698,"Unit_Nm":"City of Boulder City Parks","Pub_Access":"OA","MngNm_Desc":"City Land","MngTp_Desc":"Local Government","DesTp_Desc":"Local Park","GIS_Acres":1357}],[{"OBJECTID":90698,"Unit_Nm":"City of Boulder City Parks","Pub_Access":"OA","MngNm_Desc":"City Land","MngTp_Desc":"Local Government","DesTp_Desc":"Local Park","GIS_Acres":1357}],[{"OBJECTID":284173,"Unit_Nm":"Burke II","Pub_Access":"OA","MngNm_Desc":"City Land","MngTp_Desc":"Local Government","DesTp_Desc":"Local Other or Unknown","GIS_Acres":68}],[],[],[],[],[],[],[],[],[],[],[],[],[],[],[],[],[],[],[],[],[],[],[],[],[],[],[],[],[],[],[],[],[],[],[],[],[],[],[],[],[],[],[{"OBJECTID":173943,"Unit_Nm":"Dunn I","Pub_Access":"OA","MngNm_Desc":"City Land","MngTp_Desc":"Local Government","DesTp_Desc":"Local Other or Unknown","GIS_Acres":451}],[{"OBJECTID":173943,"Unit_Nm":"Dunn I","Pub_Access":"OA","MngNm_Desc":"City Land","MngTp_Desc":"Local Government","DesTp_Desc":"Local Other or Unknown","GIS_Acres":451}],[{"OBJECTID":5004,"Unit_Nm":"Eldorado Canyon State Park","Pub_Access":"OA","MngNm_Desc":"State Fish and Wildlife","MngTp_Desc":"State","DesTp_Desc":"State Park","GIS_Acres":1291}],[{"OBJECTID":108409,"Unit_Nm":"Anderson-Debacker","Pub_Access":"OA","MngNm_Desc":"City Land","MngTp_Desc":"Local Government","DesTp_Desc":"Local Other or Unknown","GIS_Acres":155}],[],[],[],[],[],[],[],[],[],[],[],[],[],[],[],[],[],[],[],[],[],[],[],[],[],[],[],[],[],[],[],[],[],[],[],[],[],[],[],[],[],[],[],[],[],[],[],[],[],[],[],[],[],[],[],[],[],[],[],[],[],[],[],[],[],[],[],[],[],[],[],[],[{"OBJECTID":90698,"Unit_Nm":"City of Boulder City Parks","Pub_Access":"OA","MngNm_Desc":"City Land","MngTp_Desc":"Local Government","DesTp_Desc":"Local Park","GIS_Acres":1357}],[],[],[],[],[],[],[],[],[],[],[],[],[],[],[],[],[],[],[],[],[],[],[],[],[],[],[],[],[],[{"OBJECTID":63721,"Unit_Nm":"City of Boulder City Land - Unknown","Pub_Access":"OA","MngNm_Desc":"City Land","MngTp_Desc":"Local Government","DesTp_Desc":"Local Other or Unknown","GIS_Acres":7}],[{"OBJECTID":63721,"Unit_Nm":"City of Boulder City Land - Unknown","Pub_Access":"OA","MngNm_Desc":"City Land","MngTp_Desc":"Local Government","DesTp_Desc":"Local Other or Unknown","GIS_Acres":7}],[],[{"OBJECTID":63721,"Unit_Nm":"City of Boulder City Land - Unknown","Pub_Access":"OA","MngNm_Desc":"City Land","MngTp_Desc":"Local Government","DesTp_Desc":"Local Other or Unknown","GIS_Acres":7}],[],[],[],[],[],[],[],[],[],[],[],[],[],[],[],[],[],[],[],[],[],[],[],[],[],[],[],[],[],[],[],[],[],[],[],[],[],[],[],[],[],[],[],[],[],[],[],[],[],[],[],[],[],[],[{"OBJECTID":90698,"Unit_Nm":"City of Boulder City Parks","Pub_Access":"OA","MngNm_Desc":"City Land","MngTp_Desc":"Local Government","DesTp_Desc":"Local Park","GIS_Acres":1357}],[],[],[],[],[{"OBJECTID":90698,"Unit_Nm":"City of Boulder City Parks","Pub_Access":"OA","MngNm_Desc":"City Land","MngTp_Desc":"Local Government","DesTp_Desc":"Local Park","GIS_Acres":1357}],[{"OBJECTID":90698,"Unit_Nm":"City of Boulder City Parks","Pub_Access":"OA","MngNm_Desc":"City Land","MngTp_Desc":"Local Government","DesTp_Desc":"Local Park","GIS_Acres":1357}],[{"OBJECTID":90698,"Unit_Nm":"City of Boulder City Parks","Pub_Access":"OA","MngNm_Desc":"City Land","MngTp_Desc":"Local Government","DesTp_Desc":"Local Park","GIS_Acres":1357}],[{"OBJECTID":90698,"Unit_Nm":"City of Boulder City Parks","Pub_Access":"OA","MngNm_Desc":"City Land","MngTp_Desc":"Local Government","DesTp_Desc":"Local Park","GIS_Acres":1357}],[{"OBJECTID":90698,"Unit_Nm":"City of Boulder City Parks","Pub_Access":"OA","MngNm_Desc":"City Land","MngTp_Desc":"Local Government","DesTp_Desc":"Local Park","GIS_Acres":1357}],[],[],[],[],[],[],[],[],[],[],[],[{"OBJECTID":90698,"Unit_Nm":"City of Boulder City Parks","Pub_Access":"OA","MngNm_Desc":"City Land","MngTp_Desc":"Local Government","DesTp_Desc":"Local Park","GIS_Acres":1357}],[],[],[],[],[],[],[],[{"OBJECTID":233806,"Unit_Nm":"Bergheim - Wood","Pub_Access":"OA","MngNm_Desc":"City Land","MngTp_Desc":"Local Government","DesTp_Desc":"Local Conservation Area","GIS_Acres":317}],[],[],[],[],[],[],[],[],[],[],[],[],[],[],[],[],[],[],[],[],[],[],[],[],[],[],[],[],[],[],[],[],[],[],[],[],[],[],[],[],[],[],[],[],[],[],[],[],[],[],[],[],[],[],[],[],[],[{"OBJECTID":124690,"Unit_Nm":"Austin - Russell","Pub_Access":"OA","MngNm_Desc":"City Land","MngTp_Desc":"Local Government","DesTp_Desc":"Local Other or Unknown","GIS_Acres":236}],[{"OBJECTID":124690,"Unit_Nm":"Austin - Russell","Pub_Access":"OA","MngNm_Desc":"City Land","MngTp_Desc":"Local Government","DesTp_Desc":"Local Other or Unknown","GIS_Acres":236}],[{"OBJECTID":124690,"Unit_Nm":"Austin - Russell","Pub_Access":"OA","MngNm_Desc":"City Land","MngTp_Desc":"Local Government","DesTp_Desc":"Local Other or Unknown","GIS_Acres":236}],[],[],[],[],[],[],[],[],[],[],[],[],[],[],[],[],[],[],[],[],[],[],[],[],[],[],[],[{"OBJECTID":119199,"Unit_Nm":"Boulder Mountain Parks","Pub_Access":"OA","MngNm_Desc":"City Land","MngTp_Desc":"Local Government","DesTp_Desc":"Local Other or Unknown","GIS_Acres":29}],[],[],[],[],[{"OBJECTID":119199,"Unit_Nm":"Boulder Mountain Parks","Pub_Access":"OA","MngNm_Desc":"City Land","MngTp_Desc":"Local Government","DesTp_Desc":"Local Other or Unknown","GIS_Acres":29}],[{"OBJECTID":119199,"Unit_Nm":"Boulder Mountain Parks","Pub_Access":"OA","MngNm_Desc":"City Land","MngTp_Desc":"Local Government","DesTp_Desc":"Local Other or Unknown","GIS_Acres":29}],[],[],[],[],[{"OBJECTID":119199,"Unit_Nm":"Boulder Mountain Parks","Pub_Access":"OA","MngNm_Desc":"City Land","MngTp_Desc":"Local Government","DesTp_Desc":"Local Other or Unknown","GIS_Acres":29}],[],[],[],[],[],[{"OBJECTID":119199,"Unit_Nm":"Boulder Mountain Parks","Pub_Access":"OA","MngNm_Desc":"City Land","MngTp_Desc":"Local Government","DesTp_Desc":"Local Other or Unknown","GIS_Acres":29}],[],[],[],[],[],[],[],[{"OBJECTID":124690,"Unit_Nm":"Austin - Russell","Pub_Access":"OA","MngNm_Desc":"City Land","MngTp_Desc":"Local Government","DesTp_Desc":"Local Other or Unknown","GIS_Acres":236}],[],[{"OBJECTID":124690,"Unit_Nm":"Austin - Russell","Pub_Access":"OA","MngNm_Desc":"City Land","MngTp_Desc":"Local Government","DesTp_Desc":"Local Other or Unknown","GIS_Acres":236}],[],[],[],[],[],[],[],[],[],[],[],[],[],[],[],[],[],[{"OBJECTID":119199,"Unit_Nm":"Boulder Mountain Parks","Pub_Access":"OA","MngNm_Desc":"City Land","MngTp_Desc":"Local Government","DesTp_Desc":"Local Other or Unknown","GIS_Acres":29}],[{"OBJECTID":119199,"Unit_Nm":"Boulder Mountain Parks","Pub_Access":"OA","MngNm_Desc":"City Land","MngTp_Desc":"Local Government","DesTp_Desc":"Local Other or Unknown","GIS_Acres":29}],[{"OBJECTID":61054,"Unit_Nm":"Chautauqua Park","Pub_Access":"OA","MngNm_Desc":"City Land","MngTp_Desc":"Local Government","DesTp_Desc":"Local Park","GIS_Acres":309}],[{"OBJECTID":61054,"Unit_Nm":"Chautauqua Park","Pub_Access":"OA","MngNm_Desc":"City Land","MngTp_Desc":"Local Government","DesTp_Desc":"Local Park","GIS_Acres":309}],[],[{"OBJECTID":61054,"Unit_Nm":"Chautauqua Park","Pub_Access":"OA","MngNm_Desc":"City Land","MngTp_Desc":"Local Government","DesTp_Desc":"Local Park","GIS_Acres":309}],[],[],[],[],[],[],[],[],[],[],[],[],[],[],[],[],[],[],[],[],[],[],[],[],[],[],[],[],[],[{"OBJECTID":90698,"Unit_Nm":"City of Boulder City Parks","Pub_Access":"OA","MngNm_Desc":"City Land","MngTp_Desc":"Local Government","DesTp_Desc":"Local Park","GIS_Acres":1357}],[{"OBJECTID":90698,"Unit_Nm":"City of Boulder City Parks","Pub_Access":"OA","MngNm_Desc":"City Land","MngTp_Desc":"Local Government","DesTp_Desc":"Local Park","GIS_Acres":1357}],[],[{"OBJECTID":90698,"Unit_Nm":"City of Boulder City Parks","Pub_Access":"OA","MngNm_Desc":"City Land","MngTp_Desc":"Local Government","DesTp_Desc":"Local Park","GIS_Acres":1357}],[{"OBJECTID":90698,"Unit_Nm":"City of Boulder City Parks","Pub_Access":"OA","MngNm_Desc":"City Land","MngTp_Desc":"Local Government","DesTp_Desc":"Local Park","GIS_Acres":1357}],[{"OBJECTID":90698,"Unit_Nm":"City of Boulder City Parks","Pub_Access":"OA","MngNm_Desc":"City Land","MngTp_Desc":"Local Government","DesTp_Desc":"Local Park","GIS_Acres":1357}],[],[],[],[],[],[],[],[],[],[],[],[],[],[],[{"OBJECTID":90698,"Unit_Nm":"City of Boulder City Parks","Pub_Access":"OA","MngNm_Desc":"City Land","MngTp_Desc":"Local Government","DesTp_Desc":"Local Park","GIS_Acres":1357}],[{"OBJECTID":90698,"Unit_Nm":"City of Boulder City Parks","Pub_Access":"OA","MngNm_Desc":"City Land","MngTp_Desc":"Local Government","DesTp_Desc":"Local Park","GIS_Acres":1357}],[{"OBJECTID":35745,"Unit_Nm":"Martin Park","Pub_Access":"OA","MngNm_Desc":"City Land","MngTp_Desc":"Local Government","DesTp_Desc":"Local Recreation Area","GIS_Acres":1}],[{"OBJECTID":35745,"Unit_Nm":"Martin Park","Pub_Access":"OA","MngNm_Desc":"City Land","MngTp_Desc":"Local Government","DesTp_Desc":"Local Recreation Area","GIS_Acres":1}],[{"OBJECTID":35745,"Unit_Nm":"Martin Park","Pub_Access":"OA","MngNm_Desc":"City Land","MngTp_Desc":"Local Government","DesTp_Desc":"Local Recreation Area","GIS_Acres":1}],[],[],[],[],[],[],[],[],[],[],[],[],[],[],[],[],[],[],[],[],[],[],[],[],[],[{"OBJECTID":119199,"Unit_Nm":"Boulder Mountain Parks","Pub_Access":"OA","MngNm_Desc":"City Land","MngTp_Desc":"Local Government","DesTp_Desc":"Local Other or Unknown","GIS_Acres":29}],[],[],[{"OBJECTID":119199,"Unit_Nm":"Boulder Mountain Parks","Pub_Access":"OA","MngNm_Desc":"City Land","MngTp_Desc":"Local Government","DesTp_Desc":"Local Other or Unknown","GIS_Acres":29}],[{"OBJECTID":119199,"Unit_Nm":"Boulder Mountain Parks","Pub_Access":"OA","MngNm_Desc":"City Land","MngTp_Desc":"Local Government","DesTp_Desc":"Local Other or Unknown","GIS_Acres":29}],[{"OBJECTID":119199,"Unit_Nm":"Boulder Mountain Parks","Pub_Access":"OA","MngNm_Desc":"City Land","MngTp_Desc":"Local Government","DesTp_Desc":"Local Other or Unknown","GIS_Acres":29}],[{"OBJECTID":119199,"Unit_Nm":"Boulder Mountain Parks","Pub_Access":"OA","MngNm_Desc":"City Land","MngTp_Desc":"Local Government","DesTp_Desc":"Local Other or Unknown","GIS_Acres":29}],[{"OBJECTID":82662,"Unit_Nm":"Batchelder","Pub_Access":"OA","MngNm_Desc":"City Land","MngTp_Desc":"Local Government","DesTp_Desc":"Local Other or Unknown","GIS_Acres":46}],[{"OBJECTID":119199,"Unit_Nm":"Boulder Mountain Parks","Pub_Access":"OA","MngNm_Desc":"City Land","MngTp_Desc":"Local Government","DesTp_Desc":"Local Other or Unknown","GIS_Acres":29}],[{"OBJECTID":119199,"Unit_Nm":"Boulder Mountain Parks","Pub_Access":"OA","MngNm_Desc":"City Land","MngTp_Desc":"Local Government","DesTp_Desc":"Local Other or Unknown","GIS_Acres":29}],[{"OBJECTID":119199,"Unit_Nm":"Boulder Mountain Parks","Pub_Access":"OA","MngNm_Desc":"City Land","MngTp_Desc":"Local Government","DesTp_Desc":"Local Other or Unknown","GIS_Acres":29}],[{"OBJECTID":119199,"Unit_Nm":"Boulder Mountain Parks","Pub_Access":"OA","MngNm_Desc":"City Land","MngTp_Desc":"Local Government","DesTp_Desc":"Local Other or Unknown","GIS_Acres":29}],[{"OBJECTID":119199,"Unit_Nm":"Boulder Mountain Parks","Pub_Access":"OA","MngNm_Desc":"City Land","MngTp_Desc":"Local Government","DesTp_Desc":"Local Other or Unknown","GIS_Acres":29}],[{"OBJECTID":119199,"Unit_Nm":"Boulder Mountain Parks","Pub_Access":"OA","MngNm_Desc":"City Land","MngTp_Desc":"Local Government","DesTp_Desc":"Local Other or Unknown","GIS_Acres":29}],[{"OBJECTID":119199,"Unit_Nm":"Boulder Mountain Parks","Pub_Access":"OA","MngNm_Desc":"City Land","MngTp_Desc":"Local Government","DesTp_Desc":"Local Other or Unknown","GIS_Acres":29}],[{"OBJECTID":119199,"Unit_Nm":"Boulder Mountain Parks","Pub_Access":"OA","MngNm_Desc":"City Land","MngTp_Desc":"Local Government","DesTp_Desc":"Local Other or Unknown","GIS_Acres":29}],[{"OBJECTID":119199,"Unit_Nm":"Boulder Mountain Parks","Pub_Access":"OA","MngNm_Desc":"City Land","MngTp_Desc":"Local Government","DesTp_Desc":"Local Other or Unknown","GIS_Acres":29}],[{"OBJECTID":119199,"Unit_Nm":"Boulder Mountain Parks","Pub_Access":"OA","MngNm_Desc":"City Land","MngTp_Desc":"Local Government","DesTp_Desc":"Local Other or Unknown","GIS_Acres":29}],[{"OBJECTID":119199,"Unit_Nm":"Boulder Mountain Parks","Pub_Access":"OA","MngNm_Desc":"City Land","MngTp_Desc":"Local Government","DesTp_Desc":"Local Other or Unknown","GIS_Acres":29}],[{"OBJECTID":119199,"Unit_Nm":"Boulder Mountain Parks","Pub_Access":"OA","MngNm_Desc":"City Land","MngTp_Desc":"Local Government","DesTp_Desc":"Local Other or Unknown","GIS_Acres":29}],[{"OBJECTID":119199,"Unit_Nm":"Boulder Mountain Parks","Pub_Access":"OA","MngNm_Desc":"City Land","MngTp_Desc":"Local Government","DesTp_Desc":"Local Other or Unknown","GIS_Acres":29}],[],[],[],[],[],[],[],[],[],[],[],[],[],[],[],[],[],[],[],[],[],[],[],[],[],[],[],[],[],[],[],[],[],[],[],[],[],[],[],[],[],[],[],[],[],[],[],[],[{"OBJECTID":90698,"Unit_Nm":"City of Boulder City Parks","Pub_Access":"OA","MngNm_Desc":"City Land","MngTp_Desc":"Local Government","DesTp_Desc":"Local Park","GIS_Acres":1357}],[{"OBJECTID":90698,"Unit_Nm":"City of Boulder City Parks","Pub_Access":"OA","MngNm_Desc":"City Land","MngTp_Desc":"Local Government","DesTp_Desc":"Local Park","GIS_Acres":1357}],[],[{"OBJECTID":90698,"Unit_Nm":"City of Boulder City Parks","Pub_Access":"OA","MngNm_Desc":"City Land","MngTp_Desc":"Local Government","DesTp_Desc":"Local Park","GIS_Acres":1357}],[],[],[],[],[],[{"OBJECTID":119199,"Unit_Nm":"Boulder Mountain Parks","Pub_Access":"OA","MngNm_Desc":"City Land","MngTp_Desc":"Local Government","DesTp_Desc":"Local Other or Unknown","GIS_Acres":29}],[],[],[],[],[],[],[],[],[],[],[],[],[{"OBJECTID":168577,"Unit_Nm":"Wells - West","Pub_Access":"OA","MngNm_Desc":"City Land","MngTp_Desc":"Local Government","DesTp_Desc":"Local Other or Unknown","GIS_Acres":387}],[],[],[],[],[],[],[],[],[],[],[],[],[],[],[],[{"OBJECTID":124690,"Unit_Nm":"Austin - Russell","Pub_Access":"OA","MngNm_Desc":"City Land","MngTp_Desc":"Local Government","DesTp_Desc":"Local Other or Unknown","GIS_Acres":236}],[],[],[],[],[],[],[],[],[{"OBJECTID":124690,"Unit_Nm":"Austin - Russell","Pub_Access":"OA","MngNm_Desc":"City Land","MngTp_Desc":"Local Government","DesTp_Desc":"Local Other or Unknown","GIS_Acres":236}],[],[{"OBJECTID":119199,"Unit_Nm":"Boulder Mountain Parks","Pub_Access":"OA","MngNm_Desc":"City Land","MngTp_Desc":"Local Government","DesTp_Desc":"Local Other or Unknown","GIS_Acres":29}],[{"OBJECTID":119199,"Unit_Nm":"Boulder Mountain Parks","Pub_Access":"OA","MngNm_Desc":"City Land","MngTp_Desc":"Local Government","DesTp_Desc":"Local Other or Unknown","GIS_Acres":29}],[{"OBJECTID":119199,"Unit_Nm":"Boulder Mountain Parks","Pub_Access":"OA","MngNm_Desc":"City Land","MngTp_Desc":"Local Government","DesTp_Desc":"Local Other or Unknown","GIS_Acres":29}],[],[{"OBJECTID":124690,"Unit_Nm":"Austin - Russell","Pub_Access":"OA","MngNm_Desc":"City Land","MngTp_Desc":"Local Government","DesTp_Desc":"Local Other or Unknown","GIS_Acres":236}],[],[],[],[],[],[],[],[],[],[],[],[],[],[],[],[],[],[],[],[],[],[],[],[],[],[],[],[],[],[],[],[],[],[],[],[],[],[],[],[],[],[],[],[],[],[],[],[],[],[],[],[],[],[],[],[],[],[],[],[],[],[],[],[],[],[],[],[],[],[],[],[],[],[],[],[],[],[],[],[],[],[],[],[],[],[],[],[],[],[],[],[],[],[],[],[],[],[],[],[],[],[],[],[],[],[],[],[],[],[],[],[],[{"OBJECTID":90698,"Unit_Nm":"City of Boulder City Parks","Pub_Access":"OA","MngNm_Desc":"City Land","MngTp_Desc":"Local Government","DesTp_Desc":"Local Park","GIS_Acres":1357}],[],[{"OBJECTID":90698,"Unit_Nm":"City of Boulder City Parks","Pub_Access":"OA","MngNm_Desc":"City Land","MngTp_Desc":"Local Government","DesTp_Desc":"Local Park","GIS_Acres":1357}],[],[{"OBJECTID":90698,"Unit_Nm":"City of Boulder City Parks","Pub_Access":"OA","MngNm_Desc":"City Land","MngTp_Desc":"Local Government","DesTp_Desc":"Local Park","GIS_Acres":1357}],[],[{"OBJECTID":90698,"Unit_Nm":"City of Boulder City Parks","Pub_Access":"OA","MngNm_Desc":"City Land","MngTp_Desc":"Local Government","DesTp_Desc":"Local Park","GIS_Acres":1357}],[],[{"OBJECTID":90698,"Unit_Nm":"City of Boulder City Parks","Pub_Access":"OA","MngNm_Desc":"City Land","MngTp_Desc":"Local Government","DesTp_Desc":"Local Park","GIS_Acres":1357}],[],[{"OBJECTID":90698,"Unit_Nm":"City of Boulder City Parks","Pub_Access":"OA","MngNm_Desc":"City Land","MngTp_Desc":"Local Government","DesTp_Desc":"Local Park","GIS_Acres":1357}],[{"OBJECTID":90698,"Unit_Nm":"City of Boulder City Parks","Pub_Access":"OA","MngNm_Desc":"City Land","MngTp_Desc":"Local Government","DesTp_Desc":"Local Park","GIS_Acres":1357}],[],[],[],[],[],[],[],[],[],[],[],[],[],[],[],[],[{"OBJECTID":90698,"Unit_Nm":"City of Boulder City Parks","Pub_Access":"OA","MngNm_Desc":"City Land","MngTp_Desc":"Local Government","DesTp_Desc":"Local Park","GIS_Acres":1357}],[],[],[],[],[],[],[],[],[],[{"OBJECTID":90698,"Unit_Nm":"City of Boulder City Parks","Pub_Access":"OA","MngNm_Desc":"City Land","MngTp_Desc":"Local Government","DesTp_Desc":"Local Park","GIS_Acres":1357}],[],[],[],[],[],[],[],[],[],[],[],[],[],[],[],[],[],[],[],[],[],[],[],[],[],[{"OBJECTID":90698,"Unit_Nm":"City of Boulder City Parks","Pub_Access":"OA","MngNm_Desc":"City Land","MngTp_Desc":"Local Government","DesTp_Desc":"Local Park","GIS_Acres":1357}],[{"OBJECTID":90698,"Unit_Nm":"City of Boulder City Parks","Pub_Access":"OA","MngNm_Desc":"City Land","MngTp_Desc":"Local Government","DesTp_Desc":"Local Park","GIS_Acres":1357}],[{"OBJECTID":90698,"Unit_Nm":"City of Boulder City Parks","Pub_Access":"OA","MngNm_Desc":"City Land","MngTp_Desc":"Local Government","DesTp_Desc":"Local Park","GIS_Acres":1357}],[{"OBJECTID":90698,"Unit_Nm":"City of Boulder City Parks","Pub_Access":"OA","MngNm_Desc":"City Land","MngTp_Desc":"Local Government","DesTp_Desc":"Local Park","GIS_Acres":1357}],[],[],[],[],[],[],[],[{"OBJECTID":90698,"Unit_Nm":"City of Boulder City Parks","Pub_Access":"OA","MngNm_Desc":"City Land","MngTp_Desc":"Local Government","DesTp_Desc":"Local Park","GIS_Acres":1357}],[],[],[],[],[],[{"OBJECTID":90698,"Unit_Nm":"City of Boulder City Parks","Pub_Access":"OA","MngNm_Desc":"City Land","MngTp_Desc":"Local Government","DesTp_Desc":"Local Park","GIS_Acres":1357}],[],[],[{"OBJECTID":90698,"Unit_Nm":"City of Boulder City Parks","Pub_Access":"OA","MngNm_Desc":"City Land","MngTp_Desc":"Local Government","DesTp_Desc":"Local Park","GIS_Acres":1357}],[],[],[],[],[],[],[],[],[],[],[],[],[],[],[],[],[],[],[],[],[],[],[],[],[],[],[],[],[],[],[],[],[],[],[],[],[],[],[],[],[],[],[],[],[],[],[],[],[],[],[],[],[],[],[],[],[],[],[],[],[],[],[],[],[],[],[],[],[],[],[],[],[],[],[],[],[],[],[],[],[],[],[],[],[],[],[],[],[],[],[],[],[],[],[],[],[],[],[],[],[],[],[],[],[],[],[],[],[],[],[],[],[],[],[],[],[],[],[],[],[],[],[],[],[],[],[],[],[],[],[],[],[],[],[{"OBJECTID":216747,"Unit_Nm":"Dean, Mattie","Pub_Access":"OA","MngNm_Desc":"City Land","MngTp_Desc":"Local Government","DesTp_Desc":"Local Other or Unknown","GIS_Acres":1}],[{"OBJECTID":216747,"Unit_Nm":"Dean, Mattie","Pub_Access":"OA","MngNm_Desc":"City Land","MngTp_Desc":"Local Government","DesTp_Desc":"Local Other or Unknown","GIS_Acres":1}],[],[{"OBJECTID":216747,"Unit_Nm":"Dean, Mattie","Pub_Access":"OA","MngNm_Desc":"City Land","MngTp_Desc":"Local Government","DesTp_Desc":"Local Other or Unknown","GIS_Acres":1}],[{"OBJECTID":216747,"Unit_Nm":"Dean, Mattie","Pub_Access":"OA","MngNm_Desc":"City Land","MngTp_Desc":"Local Government","DesTp_Desc":"Local Other or Unknown","GIS_Acres":1}],[{"OBJECTID":216747,"Unit_Nm":"Dean, Mattie","Pub_Access":"OA","MngNm_Desc":"City Land","MngTp_Desc":"Local Government","DesTp_Desc":"Local Other or Unknown","GIS_Acres":1}],[],[],[],[],[],[],[],[],[],[],[],[],[],[],[],[],[],[],[],[],[],[],[],[],[],[],[],[],[],[],[],[],[],[],[],[],[],[],[],[],[],[{"OBJECTID":90698,"Unit_Nm":"City of Boulder City Parks","Pub_Access":"OA","MngNm_Desc":"City Land","MngTp_Desc":"Local Government","DesTp_Desc":"Local Park","GIS_Acres":1357}],[],[],[],[],[],[],[],[],[],[],[],[],[],[],[],[],[],[],[],[],[],[],[],[],[],[{"OBJECTID":90698,"Unit_Nm":"City of Boulder City Parks","Pub_Access":"OA","MngNm_Desc":"City Land","MngTp_Desc":"Local Government","DesTp_Desc":"Local Park","GIS_Acres":1357}],[],[],[{"OBJECTID":90698,"Unit_Nm":"City of Boulder City Parks","Pub_Access":"OA","MngNm_Desc":"City Land","MngTp_Desc":"Local Government","DesTp_Desc":"Local Park","GIS_Acres":1357}],[],[],[{"OBJECTID":90698,"Unit_Nm":"City of Boulder City Parks","Pub_Access":"OA","MngNm_Desc":"City Land","MngTp_Desc":"Local Government","DesTp_Desc":"Local Park","GIS_Acres":1357}],[],[],[],[{"OBJECTID":90698,"Unit_Nm":"City of Boulder City Parks","Pub_Access":"OA","MngNm_Desc":"City Land","MngTp_Desc":"Local Government","DesTp_Desc":"Local Park","GIS_Acres":1357}],[],[],[{"OBJECTID":90698,"Unit_Nm":"City of Boulder City Parks","Pub_Access":"OA","MngNm_Desc":"City Land","MngTp_Desc":"Local Government","DesTp_Desc":"Local Park","GIS_Acres":1357}],[{"OBJECTID":90698,"Unit_Nm":"City of Boulder City Parks","Pub_Access":"OA","MngNm_Desc":"City Land","MngTp_Desc":"Local Government","DesTp_Desc":"Local Park","GIS_Acres":1357}],[{"OBJECTID":90698,"Unit_Nm":"City of Boulder City Parks","Pub_Access":"OA","MngNm_Desc":"City Land","MngTp_Desc":"Local Government","DesTp_Desc":"Local Park","GIS_Acres":1357}],[{"OBJECTID":90698,"Unit_Nm":"City of Boulder City Parks","Pub_Access":"OA","MngNm_Desc":"City Land","MngTp_Desc":"Local Government","DesTp_Desc":"Local Park","GIS_Acres":1357}],[],[],[],[],[],[],[],[],[],[],[],[],[],[],[],[{"OBJECTID":90698,"Unit_Nm":"City of Boulder City Parks","Pub_Access":"OA","MngNm_Desc":"City Land","MngTp_Desc":"Local Government","DesTp_Desc":"Local Park","GIS_Acres":1357}],[{"OBJECTID":90698,"Unit_Nm":"City of Boulder City Parks","Pub_Access":"OA","MngNm_Desc":"City Land","MngTp_Desc":"Local Government","DesTp_Desc":"Local Park","GIS_Acres":1357}],[],[],[],[],[],[],[],[],[],[],[],[{"OBJECTID":208689,"Unit_Nm":"Pospahala","Pub_Access":"OA","MngNm_Desc":"City Land","MngTp_Desc":"Local Government","DesTp_Desc":"Local Park","GIS_Acres":19}],[{"OBJECTID":208689,"Unit_Nm":"Pospahala","Pub_Access":"OA","MngNm_Desc":"City Land","MngTp_Desc":"Local Government","DesTp_Desc":"Local Park","GIS_Acres":19}],[],[],[],[{"OBJECTID":208689,"Unit_Nm":"Pospahala","Pub_Access":"OA","MngNm_Desc":"City Land","MngTp_Desc":"Local Government","DesTp_Desc":"Local Park","GIS_Acres":19}],[],[],[],[],[{"OBJECTID":208689,"Unit_Nm":"Pospahala","Pub_Access":"OA","MngNm_Desc":"City Land","MngTp_Desc":"Local Government","DesTp_Desc":"Local Park","GIS_Acres":19}],[{"OBJECTID":208689,"Unit_Nm":"Pospahala","Pub_Access":"OA","MngNm_Desc":"City Land","MngTp_Desc":"Local Government","DesTp_Desc":"Local Park","GIS_Acres":19}],[{"OBJECTID":208689,"Unit_Nm":"Pospahala","Pub_Access":"OA","MngNm_Desc":"City Land","MngTp_Desc":"Local Government","DesTp_Desc":"Local Park","GIS_Acres":19}],[{"OBJECTID":208689,"Unit_Nm":"Pospahala","Pub_Access":"OA","MngNm_Desc":"City Land","MngTp_Desc":"Local Government","DesTp_Desc":"Local Park","GIS_Acres":19}],[{"OBJECTID":208689,"Unit_Nm":"Pospahala","Pub_Access":"OA","MngNm_Desc":"City Land","MngTp_Desc":"Local Government","DesTp_Desc":"Local Park","GIS_Acres":19}],[{"OBJECTID":208689,"Unit_Nm":"Pospahala","Pub_Access":"OA","MngNm_Desc":"City Land","MngTp_Desc":"Local Government","DesTp_Desc":"Local Park","GIS_Acres":19}],[],[],[{"OBJECTID":172872,"Unit_Nm":"Eben G. Fine Park","Pub_Access":"OA","MngNm_Desc":"City Land","MngTp_Desc":"Local Government","DesTp_Desc":"Local Park","GIS_Acres":4}],[],[],[],[],[],[],[],[],[],[],[],[{"OBJECTID":90698,"Unit_Nm":"City of Boulder City Parks","Pub_Access":"OA","MngNm_Desc":"City Land","MngTp_Desc":"Local Government","DesTp_Desc":"Local Park","GIS_Acres":1357}],[{"OBJECTID":90698,"Unit_Nm":"City of Boulder City Parks","Pub_Access":"OA","MngNm_Desc":"City Land","MngTp_Desc":"Local Government","DesTp_Desc":"Local Park","GIS_Acres":1357}],[],[],[{"OBJECTID":90698,"Unit_Nm":"City of Boulder City Parks","Pub_Access":"OA","MngNm_Desc":"City Land","MngTp_Desc":"Local Government","DesTp_Desc":"Local Park","GIS_Acres":1357}],[],[],[],[],[{"OBJECTID":90698,"Unit_Nm":"City of Boulder City Parks","Pub_Access":"OA","MngNm_Desc":"City Land","MngTp_Desc":"Local Government","DesTp_Desc":"Local Park","GIS_Acres":1357}],[],[{"OBJECTID":90698,"Unit_Nm":"City of Boulder City Parks","Pub_Access":"OA","MngNm_Desc":"City Land","MngTp_Desc":"Local Government","DesTp_Desc":"Local Park","GIS_Acres":1357}],[{"OBJECTID":90698,"Unit_Nm":"City of Boulder City Parks","Pub_Access":"OA","MngNm_Desc":"City Land","MngTp_Desc":"Local Government","DesTp_Desc":"Local Park","GIS_Acres":1357}],[{"OBJECTID":90698,"Unit_Nm":"City of Boulder City Parks","Pub_Access":"OA","MngNm_Desc":"City Land","MngTp_Desc":"Local Government","DesTp_Desc":"Local Park","GIS_Acres":1357}],[],[{"OBJECTID":90698,"Unit_Nm":"City of Boulder City Parks","Pub_Access":"OA","MngNm_Desc":"City Land","MngTp_Desc":"Local Government","DesTp_Desc":"Local Park","GIS_Acres":1357}],[{"OBJECTID":90698,"Unit_Nm":"City of Boulder City Parks","Pub_Access":"OA","MngNm_Desc":"City Land","MngTp_Desc":"Local Government","DesTp_Desc":"Local Park","GIS_Acres":1357}],[],[{"OBJECTID":90698,"Unit_Nm":"City of Boulder City Parks","Pub_Access":"OA","MngNm_Desc":"City Land","MngTp_Desc":"Local Government","DesTp_Desc":"Local Park","GIS_Acres":1357}],[],[],[],[],[],[],[],[],[],[],[],[{"OBJECTID":90698,"Unit_Nm":"City of Boulder City Parks","Pub_Access":"OA","MngNm_Desc":"City Land","MngTp_Desc":"Local Government","DesTp_Desc":"Local Park","GIS_Acres":1357}],[],[{"OBJECTID":90698,"Unit_Nm":"City of Boulder City Parks","Pub_Access":"OA","MngNm_Desc":"City Land","MngTp_Desc":"Local Government","DesTp_Desc":"Local Park","GIS_Acres":1357}],[],[],[{"OBJECTID":90698,"Unit_Nm":"City of Boulder City Parks","Pub_Access":"OA","MngNm_Desc":"City Land","MngTp_Desc":"Local Government","DesTp_Desc":"Local Park","GIS_Acres":1357}],[],[{"OBJECTID":90698,"Unit_Nm":"City of Boulder City Parks","Pub_Access":"OA","MngNm_Desc":"City Land","MngTp_Desc":"Local Government","DesTp_Desc":"Local Park","GIS_Acres":1357}],[{"OBJECTID":90698,"Unit_Nm":"City of Boulder City Parks","Pub_Access":"OA","MngNm_Desc":"City Land","MngTp_Desc":"Local Government","DesTp_Desc":"Local Park","GIS_Acres":1357}],[{"OBJECTID":90698,"Unit_Nm":"City of Boulder City Parks","Pub_Access":"OA","MngNm_Desc":"City Land","MngTp_Desc":"Local Government","DesTp_Desc":"Local Park","GIS_Acres":1357}],[],[{"OBJECTID":90698,"Unit_Nm":"City of Boulder City Parks","Pub_Access":"OA","MngNm_Desc":"City Land","MngTp_Desc":"Local Government","DesTp_Desc":"Local Park","GIS_Acres":1357}],[],[],[],[{"OBJECTID":90698,"Unit_Nm":"City of Boulder City Parks","Pub_Access":"OA","MngNm_Desc":"City Land","MngTp_Desc":"Local Government","DesTp_Desc":"Local Park","GIS_Acres":1357}],[],[{"OBJECTID":90698,"Unit_Nm":"City of Boulder City Parks","Pub_Access":"OA","MngNm_Desc":"City Land","MngTp_Desc":"Local Government","DesTp_Desc":"Local Park","GIS_Acres":1357}],[{"OBJECTID":90698,"Unit_Nm":"City of Boulder City Parks","Pub_Access":"OA","MngNm_Desc":"City Land","MngTp_Desc":"Local Government","DesTp_Desc":"Local Park","GIS_Acres":1357}],[{"OBJECTID":90698,"Unit_Nm":"City of Boulder City Parks","Pub_Access":"OA","MngNm_Desc":"City Land","MngTp_Desc":"Local Government","DesTp_Desc":"Local Park","GIS_Acres":1357}],[],[{"OBJECTID":90698,"Unit_Nm":"City of Boulder City Parks","Pub_Access":"OA","MngNm_Desc":"City Land","MngTp_Desc":"Local Government","DesTp_Desc":"Local Park","GIS_Acres":1357}],[{"OBJECTID":90698,"Unit_Nm":"City of Boulder City Parks","Pub_Access":"OA","MngNm_Desc":"City Land","MngTp_Desc":"Local Government","DesTp_Desc":"Local Park","GIS_Acres":1357}],[],[],[{"OBJECTID":90698,"Unit_Nm":"City of Boulder City Parks","Pub_Access":"OA","MngNm_Desc":"City Land","MngTp_Desc":"Local Government","DesTp_Desc":"Local Park","GIS_Acres":1357}],[],[],[],[],[],[],[],[],[],[],[],[],[],[],[],[],[],[],[],[],[],[],[],[],[],[],[],[],[],[],[],[],[],[{"OBJECTID":197226,"Unit_Nm":"Campbell Robertson Park","Pub_Access":"OA","MngNm_Desc":"City Land","MngTp_Desc":"Local Government","DesTp_Desc":"Local Park","GIS_Acres":0}],[],[],[],[],[],[],[],[],[],[],[],[],[],[],[],[],[],[],[],[],[],[],[],[],[],[],[],[],[],[],[],[],[],[],[],[],[],[],[],[],[],[],[],[],[],[],[],[],[],[],[],[],[],[],[],[],[],[],[],[],[],[],[],[],[],[],[],[],[],[],[],[],[],[],[],[],[],[],[],[],[],[],[],[],[],[],[],[],[],[],[],[],[],[],[],[],[],[],[],[],[],[],[],[],[],[],[],[{"OBJECTID":153143,"Unit_Nm":"Greenleaf Park","Pub_Access":"OA","MngNm_Desc":"City Land","MngTp_Desc":"Local Government","DesTp_Desc":"Local Park","GIS_Acres":29}],[],[],[],[{"OBJECTID":153143,"Unit_Nm":"Greenleaf Park","Pub_Access":"OA","MngNm_Desc":"City Land","MngTp_Desc":"Local Government","DesTp_Desc":"Local Park","GIS_Acres":29}],[],[],[{"OBJECTID":153143,"Unit_Nm":"Greenleaf Park","Pub_Access":"OA","MngNm_Desc":"City Land","MngTp_Desc":"Local Government","DesTp_Desc":"Local Park","GIS_Acres":29}],[],[],[],[],[],[],[],[],[],[],[],[],[],[],[],[],[],[],[],[],[],[],[],[],[],[],[],[],[],[],[],[],[],[],[],[],[],[],[],[],[],[],[],[],[],[],[],[],[],[],[],[],[],[],[],[],[],[],[],[],[],[],[],[],[],[],[],[],[],[],[],[],[],[],[],[],[],[],[],[],[],[],[],[],[],[],[],[],[],[],[],[],[],[],[],[],[],[],[],[],[],[],[],[],[],[{"OBJECTID":90698,"Unit_Nm":"City of Boulder City Parks","Pub_Access":"OA","MngNm_Desc":"City Land","MngTp_Desc":"Local Government","DesTp_Desc":"Local Park","GIS_Acres":1357}],[],[],[],[],[],[],[],[],[],[],[],[{"OBJECTID":90698,"Unit_Nm":"City of Boulder City Parks","Pub_Access":"OA","MngNm_Desc":"City Land","MngTp_Desc":"Local Government","DesTp_Desc":"Local Park","GIS_Acres":1357}],[],[],[],[],[],[],[],[],[],[],[{"OBJECTID":90698,"Unit_Nm":"City of Boulder City Parks","Pub_Access":"OA","MngNm_Desc":"City Land","MngTp_Desc":"Local Government","DesTp_Desc":"Local Park","GIS_Acres":1357}],[],[],[],[],[],[],[],[],[],[],[],[],[],[],[],[],[],[],[],[],[],[],[],[],[],[],[],[],[],[{"OBJECTID":90698,"Unit_Nm":"City of Boulder City Parks","Pub_Access":"OA","MngNm_Desc":"City Land","MngTp_Desc":"Local Government","DesTp_Desc":"Local Park","GIS_Acres":1357}],[{"OBJECTID":90698,"Unit_Nm":"City of Boulder City Parks","Pub_Access":"OA","MngNm_Desc":"City Land","MngTp_Desc":"Local Government","DesTp_Desc":"Local Park","GIS_Acres":1357}],[{"OBJECTID":90698,"Unit_Nm":"City of Boulder City Parks","Pub_Access":"OA","MngNm_Desc":"City Land","MngTp_Desc":"Local Government","DesTp_Desc":"Local Park","GIS_Acres":1357}],[{"OBJECTID":90698,"Unit_Nm":"City of Boulder City Parks","Pub_Access":"OA","MngNm_Desc":"City Land","MngTp_Desc":"Local Government","DesTp_Desc":"Local Park","GIS_Acres":1357}],[],[{"OBJECTID":90698,"Unit_Nm":"City of Boulder City Parks","Pub_Access":"OA","MngNm_Desc":"City Land","MngTp_Desc":"Local Government","DesTp_Desc":"Local Park","GIS_Acres":1357}],[{"OBJECTID":90698,"Unit_Nm":"City of Boulder City Parks","Pub_Access":"OA","MngNm_Desc":"City Land","MngTp_Desc":"Local Government","DesTp_Desc":"Local Park","GIS_Acres":1357}],[],[],[],[],[{"OBJECTID":90698,"Unit_Nm":"City of Boulder City Parks","Pub_Access":"OA","MngNm_Desc":"City Land","MngTp_Desc":"Local Government","DesTp_Desc":"Local Park","GIS_Acres":1357}],[],[],[{"OBJECTID":90698,"Unit_Nm":"City of Boulder City Parks","Pub_Access":"OA","MngNm_Desc":"City Land","MngTp_Desc":"Local Government","DesTp_Desc":"Local Park","GIS_Acres":1357}],[],[{"OBJECTID":90698,"Unit_Nm":"City of Boulder City Parks","Pub_Access":"OA","MngNm_Desc":"City Land","MngTp_Desc":"Local Government","DesTp_Desc":"Local Park","GIS_Acres":1357}],[],[],[{"OBJECTID":90698,"Unit_Nm":"City of Boulder City Parks","Pub_Access":"OA","MngNm_Desc":"City Land","MngTp_Desc":"Local Government","DesTp_Desc":"Local Park","GIS_Acres":1357}],[],[],[],[],[],[],[],[],[],[],[],[],[],[],[],[],[],[],[],[],[],[],[],[{"OBJECTID":90698,"Unit_Nm":"City of Boulder City Parks","Pub_Access":"OA","MngNm_Desc":"City Land","MngTp_Desc":"Local Government","DesTp_Desc":"Local Park","GIS_Acres":1357}],[{"OBJECTID":90698,"Unit_Nm":"City of Boulder City Parks","Pub_Access":"OA","MngNm_Desc":"City Land","MngTp_Desc":"Local Government","DesTp_Desc":"Local Park","GIS_Acres":1357}],[{"OBJECTID":90698,"Unit_Nm":"City of Boulder City Parks","Pub_Access":"OA","MngNm_Desc":"City Land","MngTp_Desc":"Local Government","DesTp_Desc":"Local Park","GIS_Acres":1357}],[],[],[],[],[],[],[],[],[],[],[],[{"OBJECTID":90698,"Unit_Nm":"City of Boulder City Parks","Pub_Access":"OA","MngNm_Desc":"City Land","MngTp_Desc":"Local Government","DesTp_Desc":"Local Park","GIS_Acres":1357}],[],[],[{"OBJECTID":90698,"Unit_Nm":"City of Boulder City Parks","Pub_Access":"OA","MngNm_Desc":"City Land","MngTp_Desc":"Local Government","DesTp_Desc":"Local Park","GIS_Acres":1357}],[],[],[],[],[],[],[],[],[],[],[],[],[],[],[],[],[],[],[],[{"OBJECTID":90698,"Unit_Nm":"City of Boulder City Parks","Pub_Access":"OA","MngNm_Desc":"City Land","MngTp_Desc":"Local Government","DesTp_Desc":"Local Park","GIS_Acres":1357}],[{"OBJECTID":90698,"Unit_Nm":"City of Boulder City Parks","Pub_Access":"OA","MngNm_Desc":"City Land","MngTp_Desc":"Local Government","DesTp_Desc":"Local Park","GIS_Acres":1357}],[],[],[],[],[],[],[],[],[],[],[],[],[{"OBJECTID":90698,"Unit_Nm":"City of Boulder City Parks","Pub_Access":"OA","MngNm_Desc":"City Land","MngTp_Desc":"Local Government","DesTp_Desc":"Local Park","GIS_Acres":1357}],[],[],[],[],[],[],[],[],[],[],[],[],[],[],[],[],[],[],[],[],[{"OBJECTID":88207,"Unit_Nm":"North Boulder Recreation Center","Pub_Access":"OA","MngNm_Desc":"City Land","MngTp_Desc":"Local Government","DesTp_Desc":"Local Park","GIS_Acres":6}],[{"OBJECTID":88207,"Unit_Nm":"North Boulder Recreation Center","Pub_Access":"OA","MngNm_Desc":"City Land","MngTp_Desc":"Local Government","DesTp_Desc":"Local Park","GIS_Acres":6}],[{"OBJECTID":88207,"Unit_Nm":"North Boulder Recreation Center","Pub_Access":"OA","MngNm_Desc":"City Land","MngTp_Desc":"Local Government","DesTp_Desc":"Local Park","GIS_Acres":6}],[],[],[],[],[],[],[],[],[],[],[],[],[],[],[],[],[],[],[],[],[{"OBJECTID":90698,"Unit_Nm":"City of Boulder City Parks","Pub_Access":"OA","MngNm_Desc":"City Land","MngTp_Desc":"Local Government","DesTp_Desc":"Local Park","GIS_Acres":1357}],[],[],[],[{"OBJECTID":90698,"Unit_Nm":"City of Boulder City Parks","Pub_Access":"OA","MngNm_Desc":"City Land","MngTp_Desc":"Local Government","DesTp_Desc":"Local Park","GIS_Acres":1357}],[],[],[{"OBJECTID":88207,"Unit_Nm":"North Boulder Recreation Center","Pub_Access":"OA","MngNm_Desc":"City Land","MngTp_Desc":"Local Government","DesTp_Desc":"Local Park","GIS_Acres":6}],[{"OBJECTID":90698,"Unit_Nm":"City of Boulder City Parks","Pub_Access":"OA","MngNm_Desc":"City Land","MngTp_Desc":"Local Government","DesTp_Desc":"Local Park","GIS_Acres":1357}],[],[],[],[],[],[],[],[],[],[],[{"OBJECTID":88207,"Unit_Nm":"North Boulder Recreation Center","Pub_Access":"OA","MngNm_Desc":"City Land","MngTp_Desc":"Local Government","DesTp_Desc":"Local Park","GIS_Acres":6}],[],[{"OBJECTID":90698,"Unit_Nm":"City of Boulder City Parks","Pub_Access":"OA","MngNm_Desc":"City Land","MngTp_Desc":"Local Government","DesTp_Desc":"Local Park","GIS_Acres":1357}],[],[],[],[],[],[],[],[],[],[],[],[],[],[],[],[],[],[],[],[],[],[],[],[],[],[],[],[],[],[],[],[],[],[],[],[],[],[],[],[],[],[],[],[],[],[],[],[],[],[],[],[],[],[],[],[],[],[],[],[],[],[],[],[],[],[],[],[],[],[],[],[],[],[],[],[],[],[],[],[],[],[],[],[],[],[],[],[],[],[],[],[],[],[],[],[],[],[],[{"OBJECTID":90698,"Unit_Nm":"City of Boulder City Parks","Pub_Access":"OA","MngNm_Desc":"City Land","MngTp_Desc":"Local Government","DesTp_Desc":"Local Park","GIS_Acres":1357}],[{"OBJECTID":90698,"Unit_Nm":"City of Boulder City Parks","Pub_Access":"OA","MngNm_Desc":"City Land","MngTp_Desc":"Local Government","DesTp_Desc":"Local Park","GIS_Acres":1357}],[{"OBJECTID":90698,"Unit_Nm":"City of Boulder City Parks","Pub_Access":"OA","MngNm_Desc":"City Land","MngTp_Desc":"Local Government","DesTp_Desc":"Local Park","GIS_Acres":1357}],[],[{"OBJECTID":90698,"Unit_Nm":"City of Boulder City Parks","Pub_Access":"OA","MngNm_Desc":"City Land","MngTp_Desc":"Local Government","DesTp_Desc":"Local Park","GIS_Acres":1357}],[],[{"OBJECTID":90698,"Unit_Nm":"City of Boulder City Parks","Pub_Access":"OA","MngNm_Desc":"City Land","MngTp_Desc":"Local Government","DesTp_Desc":"Local Park","GIS_Acres":1357}],[],[{"OBJECTID":90698,"Unit_Nm":"City of Boulder City Parks","Pub_Access":"OA","MngNm_Desc":"City Land","MngTp_Desc":"Local Government","DesTp_Desc":"Local Park","GIS_Acres":1357}],[],[],[],[{"OBJECTID":90698,"Unit_Nm":"City of Boulder City Parks","Pub_Access":"OA","MngNm_Desc":"City Land","MngTp_Desc":"Local Government","DesTp_Desc":"Local Park","GIS_Acres":1357}],[],[],[],[],[],[],[],[],[],[],[],[],[],[],[],[],[],[],[],[],[],[],[],[],[],[],[],[],[],[],[],[],[],[],[],[],[],[],[],[],[],[],[],[],[],[],[],[],[{"OBJECTID":90698,"Unit_Nm":"City of Boulder City Parks","Pub_Access":"OA","MngNm_Desc":"City Land","MngTp_Desc":"Local Government","DesTp_Desc":"Local Park","GIS_Acres":1357}],[],[{"OBJECTID":90698,"Unit_Nm":"City of Boulder City Parks","Pub_Access":"OA","MngNm_Desc":"City Land","MngTp_Desc":"Local Government","DesTp_Desc":"Local Park","GIS_Acres":1357}],[{"OBJECTID":90698,"Unit_Nm":"City of Boulder City Parks","Pub_Access":"OA","MngNm_Desc":"City Land","MngTp_Desc":"Local Government","DesTp_Desc":"Local Park","GIS_Acres":1357}],[{"OBJECTID":90698,"Unit_Nm":"City of Boulder City Parks","Pub_Access":"OA","MngNm_Desc":"City Land","MngTp_Desc":"Local Government","DesTp_Desc":"Local Park","GIS_Acres":1357}],[{"OBJECTID":90698,"Unit_Nm":"City of Boulder City Parks","Pub_Access":"OA","MngNm_Desc":"City Land","MngTp_Desc":"Local Government","DesTp_Desc":"Local Park","GIS_Acres":1357}],[],[],[],[],[{"OBJECTID":90698,"Unit_Nm":"City of Boulder City Parks","Pub_Access":"OA","MngNm_Desc":"City Land","MngTp_Desc":"Local Government","DesTp_Desc":"Local Park","GIS_Acres":1357}],[],[{"OBJECTID":90698,"Unit_Nm":"City of Boulder City Parks","Pub_Access":"OA","MngNm_Desc":"City Land","MngTp_Desc":"Local Government","DesTp_Desc":"Local Park","GIS_Acres":1357}],[{"OBJECTID":90698,"Unit_Nm":"City of Boulder City Parks","Pub_Access":"OA","MngNm_Desc":"City Land","MngTp_Desc":"Local Government","DesTp_Desc":"Local Park","GIS_Acres":1357}],[],[{"OBJECTID":90698,"Unit_Nm":"City of Boulder City Parks","Pub_Access":"OA","MngNm_Desc":"City Land","MngTp_Desc":"Local Government","DesTp_Desc":"Local Park","GIS_Acres":1357}],[{"OBJECTID":90698,"Unit_Nm":"City of Boulder City Parks","Pub_Access":"OA","MngNm_Desc":"City Land","MngTp_Desc":"Local Government","DesTp_Desc":"Local Park","GIS_Acres":1357}],[],[],[],[],[],[],[],[],[{"OBJECTID":90698,"Unit_Nm":"City of Boulder City Parks","Pub_Access":"OA","MngNm_Desc":"City Land","MngTp_Desc":"Local Government","DesTp_Desc":"Local Park","GIS_Acres":1357}],[],[],[],[],[],[],[],[],[{"OBJECTID":90698,"Unit_Nm":"City of Boulder City Parks","Pub_Access":"OA","MngNm_Desc":"City Land","MngTp_Desc":"Local Government","DesTp_Desc":"Local Park","GIS_Acres":1357}],[],[{"OBJECTID":90698,"Unit_Nm":"City of Boulder City Parks","Pub_Access":"OA","MngNm_Desc":"City Land","MngTp_Desc":"Local Government","DesTp_Desc":"Local Park","GIS_Acres":1357}],[],[],[],[],[{"OBJECTID":90698,"Unit_Nm":"City of Boulder City Parks","Pub_Access":"OA","MngNm_Desc":"City Land","MngTp_Desc":"Local Government","DesTp_Desc":"Local Park","GIS_Acres":1357}],[{"OBJECTID":90698,"Unit_Nm":"City of Boulder City Parks","Pub_Access":"OA","MngNm_Desc":"City Land","MngTp_Desc":"Local Government","DesTp_Desc":"Local Park","GIS_Acres":1357}],[{"OBJECTID":90698,"Unit_Nm":"City of Boulder City Parks","Pub_Access":"OA","MngNm_Desc":"City Land","MngTp_Desc":"Local Government","DesTp_Desc":"Local Park","GIS_Acres":1357}],[{"OBJECTID":90698,"Unit_Nm":"City of Boulder City Parks","Pub_Access":"OA","MngNm_Desc":"City Land","MngTp_Desc":"Local Government","DesTp_Desc":"Local Park","GIS_Acres":1357}],[{"OBJECTID":90698,"Unit_Nm":"City of Boulder City Parks","Pub_Access":"OA","MngNm_Desc":"City Land","MngTp_Desc":"Local Government","DesTp_Desc":"Local Park","GIS_Acres":1357}],[],[{"OBJECTID":90698,"Unit_Nm":"City of Boulder City Parks","Pub_Access":"OA","MngNm_Desc":"City Land","MngTp_Desc":"Local Government","DesTp_Desc":"Local Park","GIS_Acres":1357}],[],[],[{"OBJECTID":90698,"Unit_Nm":"City of Boulder City Parks","Pub_Access":"OA","MngNm_Desc":"City Land","MngTp_Desc":"Local Government","DesTp_Desc":"Local Park","GIS_Acres":1357}],[],[],[],[],[],[],[],[],[],[],[],[],[],[],[],[],[],[],[],[],[],[],[],[],[],[],[],[],[],[],[],[],[],[],[],[],[],[],[],[],[],[],[],[],[],[],[],[],[],[],[],[],[],[{"OBJECTID":90698,"Unit_Nm":"City of Boulder City Parks","Pub_Access":"OA","MngNm_Desc":"City Land","MngTp_Desc":"Local Government","DesTp_Desc":"Local Park","GIS_Acres":1357}],[],[],[],[],[],[],[],[],[],[],[],[],[],[],[],[],[],[],[],[],[],[],[],[],[],[],[],[],[],[],[],[],[],[],[],[],[],[],[],[],[],[],[],[],[],[],[],[],[],[],[],[],[],[],[],[],[],[],[],[],[],[],[],[],[],[],[],[],[],[],[],[],[],[],[],[],[],[],[],[],[],[],[],[{"OBJECTID":90698,"Unit_Nm":"City of Boulder City Parks","Pub_Access":"OA","MngNm_Desc":"City Land","MngTp_Desc":"Local Government","DesTp_Desc":"Local Park","GIS_Acres":1357}],[],[{"OBJECTID":90698,"Unit_Nm":"City of Boulder City Parks","Pub_Access":"OA","MngNm_Desc":"City Land","MngTp_Desc":"Local Government","DesTp_Desc":"Local Park","GIS_Acres":1357}],[],[],[],[],[{"OBJECTID":90698,"Unit_Nm":"City of Boulder City Parks","Pub_Access":"OA","MngNm_Desc":"City Land","MngTp_Desc":"Local Government","DesTp_Desc":"Local Park","GIS_Acres":1357}],[],[],[],[],[],[],[],[],[],[],[],[],[],[],[],[],[],[],[],[],[],[],[],[],[],[{"OBJECTID":90698,"Unit_Nm":"City of Boulder City Parks","Pub_Access":"OA","MngNm_Desc":"City Land","MngTp_Desc":"Local Government","DesTp_Desc":"Local Park","GIS_Acres":1357}],[{"OBJECTID":90698,"Unit_Nm":"City of Boulder City Parks","Pub_Access":"OA","MngNm_Desc":"City Land","MngTp_Desc":"Local Government","DesTp_Desc":"Local Park","GIS_Acres":1357}],[{"OBJECTID":90698,"Unit_Nm":"City of Boulder City Parks","Pub_Access":"OA","MngNm_Desc":"City Land","MngTp_Desc":"Local Government","DesTp_Desc":"Local Park","GIS_Acres":1357}],[],[],[],[],[],[],[],[],[],[],[],[],[],[],[],[],[],[],[],[],[],[],[],[],[],[],[{"OBJECTID":90698,"Unit_Nm":"City of Boulder City Parks","Pub_Access":"OA","MngNm_Desc":"City Land","MngTp_Desc":"Local Government","DesTp_Desc":"Local Park","GIS_Acres":1357}],[],[],[],[],[],[{"OBJECTID":208689,"Unit_Nm":"Pospahala","Pub_Access":"OA","MngNm_Desc":"City Land","MngTp_Desc":"Local Government","DesTp_Desc":"Local Park","GIS_Acres":19}],[],[],[{"OBJECTID":90698,"Unit_Nm":"City of Boulder City Parks","Pub_Access":"OA","MngNm_Desc":"City Land","MngTp_Desc":"Local Government","DesTp_Desc":"Local Park","GIS_Acres":1357}],[],[],[],[],[],[],[],[],[],[],[],[],[],[],[],[],[],[],[],[],[],[],[],[],[],[],[],[],[],[],[],[{"OBJECTID":90698,"Unit_Nm":"City of Boulder City Parks","Pub_Access":"OA","MngNm_Desc":"City Land","MngTp_Desc":"Local Government","DesTp_Desc":"Local Park","GIS_Acres":1357}],[{"OBJECTID":90698,"Unit_Nm":"City of Boulder City Parks","Pub_Access":"OA","MngNm_Desc":"City Land","MngTp_Desc":"Local Government","DesTp_Desc":"Local Park","GIS_Acres":1357}],[{"OBJECTID":90698,"Unit_Nm":"City of Boulder City Parks","Pub_Access":"OA","MngNm_Desc":"City Land","MngTp_Desc":"Local Government","DesTp_Desc":"Local Park","GIS_Acres":1357}],[],[],[],[],[],[],[],[],[],[],[],[],[],[],[],[],[],[],[],[],[],[],[],[],[],[],[],[],[],[],[],[],[],[],[],[],[],[],[],[],[],[],[],[],[],[],[],[],[],[],[],[],[],[],[],[],[],[],[],[],[],[],[],[],[],[],[],[],[],[],[],[],[{"OBJECTID":90698,"Unit_Nm":"City of Boulder City Parks","Pub_Access":"OA","MngNm_Desc":"City Land","MngTp_Desc":"Local Government","DesTp_Desc":"Local Park","GIS_Acres":1357}],[],[],[],[],[],[],[],[],[],[],[],[],[],[{"OBJECTID":88207,"Unit_Nm":"North Boulder Recreation Center","Pub_Access":"OA","MngNm_Desc":"City Land","MngTp_Desc":"Local Government","DesTp_Desc":"Local Park","GIS_Acres":6}],[],[],[],[],[],[],[],[],[],[],[],[],[],[],[],[],[],[],[],[],[],[],[],[],[],[],[],[],[],[],[],[],[],[],[],[],[],[],[],[],[],[],[],[],[],[],[],[],[],[],[],[],[],[],[],[],[],[],[],[],[],[],[],[],[],[],[],[],[],[{"OBJECTID":90698,"Unit_Nm":"City of Boulder City Parks","Pub_Access":"OA","MngNm_Desc":"City Land","MngTp_Desc":"Local Government","DesTp_Desc":"Local Park","GIS_Acres":1357}],[],[],[],[],[],[],[],[],[],[],[],[],[],[],[],[],[{"OBJECTID":90698,"Unit_Nm":"City of Boulder City Parks","Pub_Access":"OA","MngNm_Desc":"City Land","MngTp_Desc":"Local Government","DesTp_Desc":"Local Park","GIS_Acres":1357}],[],[],[{"OBJECTID":172872,"Unit_Nm":"Eben G. Fine Park","Pub_Access":"OA","MngNm_Desc":"City Land","MngTp_Desc":"Local Government","DesTp_Desc":"Local Park","GIS_Acres":4}],[{"OBJECTID":208689,"Unit_Nm":"Pospahala","Pub_Access":"OA","MngNm_Desc":"City Land","MngTp_Desc":"Local Government","DesTp_Desc":"Local Park","GIS_Acres":19}],[{"OBJECTID":6254,"Unit_Nm":"Thorne I","Pub_Access":"OA","MngNm_Desc":"City Land","MngTp_Desc":"Local Government","DesTp_Desc":"Local Other or Unknown","GIS_Acres":1}],[],[],[],[],[],[],[],[],[],[],[],[],[],[{"OBJECTID":229588,"Unit_Nm":"Alvin New","Pub_Access":"OA","MngNm_Desc":"City Land","MngTp_Desc":"Local Government","DesTp_Desc":"Local Other or Unknown","GIS_Acres":20}],[],[],[],[],[],[],[],[],[],[],[],[],[],[],[],[],[],[],[],[],[],[],[],[],[],[],[],[{"OBJECTID":90698,"Unit_Nm":"City of Boulder City Parks","Pub_Access":"OA","MngNm_Desc":"City Land","MngTp_Desc":"Local Government","DesTp_Desc":"Local Park","GIS_Acres":1357}],[{"OBJECTID":90698,"Unit_Nm":"City of Boulder City Parks","Pub_Access":"OA","MngNm_Desc":"City Land","MngTp_Desc":"Local Government","DesTp_Desc":"Local Park","GIS_Acres":1357}],[],[],[],[],[],[],[],[],[],[],[],[],[],[],[],[],[],[],[],[],[],[],[],[],[],[],[],[],[],[],[],[],[],[],[],[],[],[],[],[],[],[{"OBJECTID":90698,"Unit_Nm":"City of Boulder City Parks","Pub_Access":"OA","MngNm_Desc":"City Land","MngTp_Desc":"Local Government","DesTp_Desc":"Local Park","GIS_Acres":1357}],[{"OBJECTID":90698,"Unit_Nm":"City of Boulder City Parks","Pub_Access":"OA","MngNm_Desc":"City Land","MngTp_Desc":"Local Government","DesTp_Desc":"Local Park","GIS_Acres":1357}],[],[{"OBJECTID":90698,"Unit_Nm":"City of Boulder City Parks","Pub_Access":"OA","MngNm_Desc":"City Land","MngTp_Desc":"Local Government","DesTp_Desc":"Local Park","GIS_Acres":1357}],[],[],[],[{"OBJECTID":90698,"Unit_Nm":"City of Boulder City Parks","Pub_Access":"OA","MngNm_Desc":"City Land","MngTp_Desc":"Local Government","DesTp_Desc":"Local Park","GIS_Acres":1357}],[],[{"OBJECTID":90698,"Unit_Nm":"City of Boulder City Parks","Pub_Access":"OA","MngNm_Desc":"City Land","MngTp_Desc":"Local Government","DesTp_Desc":"Local Park","GIS_Acres":1357}],[],[],[],[],[],[],[],[],[],[],[],[],[],[],[],[],[],[],[],[],[],[],[],[],[],[],[],[],[],[],[],[],[],[],[],[],[],[],[],[],[],[],[],[],[],[],[],[],[],[],[],[],[],[],[],[],[],[],[{"OBJECTID":90698,"Unit_Nm":"City of Boulder City Parks","Pub_Access":"OA","MngNm_Desc":"City Land","MngTp_Desc":"Local Government","DesTp_Desc":"Local Park","GIS_Acres":1357}],[{"OBJECTID":90698,"Unit_Nm":"City of Boulder City Parks","Pub_Access":"OA","MngNm_Desc":"City Land","MngTp_Desc":"Local Government","DesTp_Desc":"Local Park","GIS_Acres":1357}],[{"OBJECTID":90698,"Unit_Nm":"City of Boulder City Parks","Pub_Access":"OA","MngNm_Desc":"City Land","MngTp_Desc":"Local Government","DesTp_Desc":"Local Park","GIS_Acres":1357}],[{"OBJECTID":90698,"Unit_Nm":"City of Boulder City Parks","Pub_Access":"OA","MngNm_Desc":"City Land","MngTp_Desc":"Local Government","DesTp_Desc":"Local Park","GIS_Acres":1357}],[],[],[],[],[{"OBJECTID":90698,"Unit_Nm":"City of Boulder City Parks","Pub_Access":"OA","MngNm_Desc":"City Land","MngTp_Desc":"Local Government","DesTp_Desc":"Local Park","GIS_Acres":1357}],[{"OBJECTID":90698,"Unit_Nm":"City of Boulder City Parks","Pub_Access":"OA","MngNm_Desc":"City Land","MngTp_Desc":"Local Government","DesTp_Desc":"Local Park","GIS_Acres":1357}],[],[],[],[{"OBJECTID":208689,"Unit_Nm":"Pospahala","Pub_Access":"OA","MngNm_Desc":"City Land","MngTp_Desc":"Local Government","DesTp_Desc":"Local Park","GIS_Acres":19}],[],[],[],[],[],[],[],[],[{"OBJECTID":111219,"Unit_Nm":"Evert Pierson Memorial Kids' Fishing Ponds","Pub_Access":"OA","MngNm_Desc":"City Land","MngTp_Desc":"Local Government","DesTp_Desc":"Local Recreation Area","GIS_Acres":4}],[],[],[],[],[],[],[],[],[{"OBJECTID":90698,"Unit_Nm":"City of Boulder City Parks","Pub_Access":"OA","MngNm_Desc":"City Land","MngTp_Desc":"Local Government","DesTp_Desc":"Local Park","GIS_Acres":1357}],[],[{"OBJECTID":90698,"Unit_Nm":"City of Boulder City Parks","Pub_Access":"OA","MngNm_Desc":"City Land","MngTp_Desc":"Local Government","DesTp_Desc":"Local Park","GIS_Acres":1357}],[],[],[{"OBJECTID":90698,"Unit_Nm":"City of Boulder City Parks","Pub_Access":"OA","MngNm_Desc":"City Land","MngTp_Desc":"Local Government","DesTp_Desc":"Local Park","GIS_Acres":1357}],[],[{"OBJECTID":90698,"Unit_Nm":"City of Boulder City Parks","Pub_Access":"OA","MngNm_Desc":"City Land","MngTp_Desc":"Local Government","DesTp_Desc":"Local Park","GIS_Acres":1357}],[{"OBJECTID":90698,"Unit_Nm":"City of Boulder City Parks","Pub_Access":"OA","MngNm_Desc":"City Land","MngTp_Desc":"Local Government","DesTp_Desc":"Local Park","GIS_Acres":1357}],[{"OBJECTID":90698,"Unit_Nm":"City of Boulder City Parks","Pub_Access":"OA","MngNm_Desc":"City Land","MngTp_Desc":"Local Government","DesTp_Desc":"Local Park","GIS_Acres":1357}],[],[],[{"OBJECTID":90698,"Unit_Nm":"City of Boulder City Parks","Pub_Access":"OA","MngNm_Desc":"City Land","MngTp_Desc":"Local Government","DesTp_Desc":"Local Park","GIS_Acres":1357}],[],[],[],[],[],[],[],[],[],[],[],[],[],[{"OBJECTID":90698,"Unit_Nm":"City of Boulder City Parks","Pub_Access":"OA","MngNm_Desc":"City Land","MngTp_Desc":"Local Government","DesTp_Desc":"Local Park","GIS_Acres":1357}],[],[],[],[],[],[],[],[],[],[],[],[],[],[],[],[],[],[],[],[],[],[],[],[],[],[],[],[],[],[],[],[],[],[],[],[],[],[{"OBJECTID":153143,"Unit_Nm":"Greenleaf Park","Pub_Access":"OA","MngNm_Desc":"City Land","MngTp_Desc":"Local Government","DesTp_Desc":"Local Park","GIS_Acres":29}],[],[],[{"OBJECTID":153143,"Unit_Nm":"Greenleaf Park","Pub_Access":"OA","MngNm_Desc":"City Land","MngTp_Desc":"Local Government","DesTp_Desc":"Local Park","GIS_Acres":29}],[],[],[],[],[],[],[],[],[],[],[],[],[],[],[],[],[],[],[],[],[],[],[],[],[],[],[],[],[],[],[],[],[],[],[],[],[],[],[],[],[],[],[],[],[],[],[],[],[],[],[],[{"OBJECTID":90698,"Unit_Nm":"City of Boulder City Parks","Pub_Access":"OA","MngNm_Desc":"City Land","MngTp_Desc":"Local Government","DesTp_Desc":"Local Park","GIS_Acres":1357}],[],[],[],[],[],[{"OBJECTID":90698,"Unit_Nm":"City of Boulder City Parks","Pub_Access":"OA","MngNm_Desc":"City Land","MngTp_Desc":"Local Government","DesTp_Desc":"Local Park","GIS_Acres":1357}],[{"OBJECTID":90698,"Unit_Nm":"City of Boulder City Parks","Pub_Access":"OA","MngNm_Desc":"City Land","MngTp_Desc":"Local Government","DesTp_Desc":"Local Park","GIS_Acres":1357}],[{"OBJECTID":90698,"Unit_Nm":"City of Boulder City Parks","Pub_Access":"OA","MngNm_Desc":"City Land","MngTp_Desc":"Local Government","DesTp_Desc":"Local Park","GIS_Acres":1357}],[],[],[],[{"OBJECTID":90698,"Unit_Nm":"City of Boulder City Parks","Pub_Access":"OA","MngNm_Desc":"City Land","MngTp_Desc":"Local Government","DesTp_Desc":"Local Park","GIS_Acres":1357}],[],[],[{"OBJECTID":90698,"Unit_Nm":"City of Boulder City Parks","Pub_Access":"OA","MngNm_Desc":"City Land","MngTp_Desc":"Local Government","DesTp_Desc":"Local Park","GIS_Acres":1357}],[],[],[{"OBJECTID":88207,"Unit_Nm":"North Boulder Recreation Center","Pub_Access":"OA","MngNm_Desc":"City Land","MngTp_Desc":"Local Government","DesTp_Desc":"Local Park","GIS_Acres":6}],[],[{"OBJECTID":88207,"Unit_Nm":"North Boulder Recreation Center","Pub_Access":"OA","MngNm_Desc":"City Land","MngTp_Desc":"Local Government","DesTp_Desc":"Local Park","GIS_Acres":6}],[],[{"OBJECTID":88207,"Unit_Nm":"North Boulder Recreation Center","Pub_Access":"OA","MngNm_Desc":"City Land","MngTp_Desc":"Local Government","DesTp_Desc":"Local Park","GIS_Acres":6}],[{"OBJECTID":90698,"Unit_Nm":"City of Boulder City Parks","Pub_Access":"OA","MngNm_Desc":"City Land","MngTp_Desc":"Local Government","DesTp_Desc":"Local Park","GIS_Acres":1357}],[{"OBJECTID":90698,"Unit_Nm":"City of Boulder City Parks","Pub_Access":"OA","MngNm_Desc":"City Land","MngTp_Desc":"Local Government","DesTp_Desc":"Local Park","GIS_Acres":1357}],[{"OBJECTID":90698,"Unit_Nm":"City of Boulder City Parks","Pub_Access":"OA","MngNm_Desc":"City Land","MngTp_Desc":"Local Government","DesTp_Desc":"Local Park","GIS_Acres":1357}],[],[{"OBJECTID":90698,"Unit_Nm":"City of Boulder City Parks","Pub_Access":"OA","MngNm_Desc":"City Land","MngTp_Desc":"Local Government","DesTp_Desc":"Local Park","GIS_Acres":1357}],[{"OBJECTID":90698,"Unit_Nm":"City of Boulder City Parks","Pub_Access":"OA","MngNm_Desc":"City Land","MngTp_Desc":"Local Government","DesTp_Desc":"Local Park","GIS_Acres":1357}],[],[],[],[],[],[],[],[],[],[],[],[],[],[],[],[],[{"OBJECTID":159730,"Unit_Nm":"Elmer'S Two Mile Park","Pub_Access":"OA","MngNm_Desc":"City Land","MngTp_Desc":"Local Government","DesTp_Desc":"Local Park","GIS_Acres":5}],[],[{"OBJECTID":159730,"Unit_Nm":"Elmer'S Two Mile Park","Pub_Access":"OA","MngNm_Desc":"City Land","MngTp_Desc":"Local Government","DesTp_Desc":"Local Park","GIS_Acres":5}],[],[],[],[],[],[],[],[],[],[],[],[],[],[],[{"OBJECTID":90698,"Unit_Nm":"City of Boulder City Parks","Pub_Access":"OA","MngNm_Desc":"City Land","MngTp_Desc":"Local Government","DesTp_Desc":"Local Park","GIS_Acres":1357}],[{"OBJECTID":90698,"Unit_Nm":"City of Boulder City Parks","Pub_Access":"OA","MngNm_Desc":"City Land","MngTp_Desc":"Local Government","DesTp_Desc":"Local Park","GIS_Acres":1357}],[],[],[{"OBJECTID":90698,"Unit_Nm":"City of Boulder City Parks","Pub_Access":"OA","MngNm_Desc":"City Land","MngTp_Desc":"Local Government","DesTp_Desc":"Local Park","GIS_Acres":1357}],[],[],[],[],[],[{"OBJECTID":90698,"Unit_Nm":"City of Boulder City Parks","Pub_Access":"OA","MngNm_Desc":"City Land","MngTp_Desc":"Local Government","DesTp_Desc":"Local Park","GIS_Acres":1357}],[],[],[],[],[],[],[],[],[],[],[],[],[],[],[],[],[],[],[],[],[],[],[],[],[],[],[],[],[],[],[],[{"OBJECTID":90698,"Unit_Nm":"City of Boulder City Parks","Pub_Access":"OA","MngNm_Desc":"City Land","MngTp_Desc":"Local Government","DesTp_Desc":"Local Park","GIS_Acres":1357}],[],[],[],[],[],[],[],[],[],[],[],[],[],[],[],[],[],[],[],[],[],[],[],[],[],[],[],[],[],[],[],[],[],[],[],[],[],[],[],[],[],[],[],[],[],[],[],[],[],[],[],[{"OBJECTID":289032,"Unit_Nm":"Moore, Ann And Donald","Pub_Access":"OA","MngNm_Desc":"City Land","MngTp_Desc":"Local Government","DesTp_Desc":"Local Other or Unknown","GIS_Acres":4}],[],[],[],[],[],[],[],[],[],[{"OBJECTID":90698,"Unit_Nm":"City of Boulder City Parks","Pub_Access":"OA","MngNm_Desc":"City Land","MngTp_Desc":"Local Government","DesTp_Desc":"Local Park","GIS_Acres":1357}],[{"OBJECTID":90698,"Unit_Nm":"City of Boulder City Parks","Pub_Access":"OA","MngNm_Desc":"City Land","MngTp_Desc":"Local Government","DesTp_Desc":"Local Park","GIS_Acres":1357}],[{"OBJECTID":90698,"Unit_Nm":"City of Boulder City Parks","Pub_Access":"OA","MngNm_Desc":"City Land","MngTp_Desc":"Local Government","DesTp_Desc":"Local Park","GIS_Acres":1357}],[],[{"OBJECTID":208689,"Unit_Nm":"Pospahala","Pub_Access":"OA","MngNm_Desc":"City Land","MngTp_Desc":"Local Government","DesTp_Desc":"Local Park","GIS_Acres":19}],[{"OBJECTID":90698,"Unit_Nm":"City of Boulder City Parks","Pub_Access":"OA","MngNm_Desc":"City Land","MngTp_Desc":"Local Government","DesTp_Desc":"Local Park","GIS_Acres":1357}],[{"OBJECTID":90698,"Unit_Nm":"City of Boulder City Parks","Pub_Access":"OA","MngNm_Desc":"City Land","MngTp_Desc":"Local Government","DesTp_Desc":"Local Park","GIS_Acres":1357}],[],[],[],[],[],[],[],[],[],[],[],[],[],[],[],[{"OBJECTID":90698,"Unit_Nm":"City of Boulder City Parks","Pub_Access":"OA","MngNm_Desc":"City Land","MngTp_Desc":"Local Government","DesTp_Desc":"Local Park","GIS_Acres":1357}],[{"OBJECTID":90698,"Unit_Nm":"City of Boulder City Parks","Pub_Access":"OA","MngNm_Desc":"City Land","MngTp_Desc":"Local Government","DesTp_Desc":"Local Park","GIS_Acres":1357}],[{"OBJECTID":90698,"Unit_Nm":"City of Boulder City Parks","Pub_Access":"OA","MngNm_Desc":"City Land","MngTp_Desc":"Local Government","DesTp_Desc":"Local Park","GIS_Acres":1357}],[{"OBJECTID":90698,"Unit_Nm":"City of Boulder City Parks","Pub_Access":"OA","MngNm_Desc":"City Land","MngTp_Desc":"Local Government","DesTp_Desc":"Local Park","GIS_Acres":1357}],[],[],[],[],[],[],[],[],[],[{"OBJECTID":90698,"Unit_Nm":"City of Boulder City Parks","Pub_Access":"OA","MngNm_Desc":"City Land","MngTp_Desc":"Local Government","DesTp_Desc":"Local Park","GIS_Acres":1357}],[],[],[],[],[],[],[],[],[],[],[],[],[],[],[],[],[],[],[],[],[],[],[],[],[],[],[],[],[],[],[],[],[],[{"OBJECTID":90698,"Unit_Nm":"City of Boulder City Parks","Pub_Access":"OA","MngNm_Desc":"City Land","MngTp_Desc":"Local Government","DesTp_Desc":"Local Park","GIS_Acres":1357}],[],[{"OBJECTID":153143,"Unit_Nm":"Greenleaf Park","Pub_Access":"OA","MngNm_Desc":"City Land","MngTp_Desc":"Local Government","DesTp_Desc":"Local Park","GIS_Acres":29}],[{"OBJECTID":153143,"Unit_Nm":"Greenleaf Park","Pub_Access":"OA","MngNm_Desc":"City Land","MngTp_Desc":"Local Government","DesTp_Desc":"Local Park","GIS_Acres":29}],[{"OBJECTID":153143,"Unit_Nm":"Greenleaf Park","Pub_Access":"OA","MngNm_Desc":"City Land","MngTp_Desc":"Local Government","DesTp_Desc":"Local Park","GIS_Acres":29}],[{"OBJECTID":153143,"Unit_Nm":"Greenleaf Park","Pub_Access":"OA","MngNm_Desc":"City Land","MngTp_Desc":"Local Government","DesTp_Desc":"Local Park","GIS_Acres":29}],[{"OBJECTID":153143,"Unit_Nm":"Greenleaf Park","Pub_Access":"OA","MngNm_Desc":"City Land","MngTp_Desc":"Local Government","DesTp_Desc":"Local Park","GIS_Acres":29}],[],[],[],[],[],[],[],[],[],[],[],[],[],[],[],[],[],[],[],[],[],[],[],[],[],[],[{"OBJECTID":249842,"Unit_Nm":"Herzer","Pub_Access":"OA","MngNm_Desc":"City Land","MngTp_Desc":"Local Government","DesTp_Desc":"Local Other or Unknown","GIS_Acres":22}],[],[],[],[],[],[],[],[],[],[],[],[],[],[],[{"OBJECTID":90698,"Unit_Nm":"City of Boulder City Parks","Pub_Access":"OA","MngNm_Desc":"City Land","MngTp_Desc":"Local Government","DesTp_Desc":"Local Park","GIS_Acres":1357}],[],[],[],[],[],[],[],[],[],[{"OBJECTID":90698,"Unit_Nm":"City of Boulder City Parks","Pub_Access":"OA","MngNm_Desc":"City Land","MngTp_Desc":"Local Government","DesTp_Desc":"Local Park","GIS_Acres":1357}],[{"OBJECTID":90698,"Unit_Nm":"City of Boulder City Parks","Pub_Access":"OA","MngNm_Desc":"City Land","MngTp_Desc":"Local Government","DesTp_Desc":"Local Park","GIS_Acres":1357}],[],[{"OBJECTID":88207,"Unit_Nm":"North Boulder Recreation Center","Pub_Access":"OA","MngNm_Desc":"City Land","MngTp_Desc":"Local Government","DesTp_Desc":"Local Park","GIS_Acres":6}],[],[{"OBJECTID":88207,"Unit_Nm":"North Boulder Recreation Center","Pub_Access":"OA","MngNm_Desc":"City Land","MngTp_Desc":"Local Government","DesTp_Desc":"Local Park","GIS_Acres":6}],[],[],[],[],[],[],[],[],[],[],[],[],[],[],[],[],[],[],[],[],[],[{"OBJECTID":90698,"Unit_Nm":"City of Boulder City Parks","Pub_Access":"OA","MngNm_Desc":"City Land","MngTp_Desc":"Local Government","DesTp_Desc":"Local Park","GIS_Acres":1357}],[{"OBJECTID":90698,"Unit_Nm":"City of Boulder City Parks","Pub_Access":"OA","MngNm_Desc":"City Land","MngTp_Desc":"Local Government","DesTp_Desc":"Local Park","GIS_Acres":1357}],[{"OBJECTID":90698,"Unit_Nm":"City of Boulder City Parks","Pub_Access":"OA","MngNm_Desc":"City Land","MngTp_Desc":"Local Government","DesTp_Desc":"Local Park","GIS_Acres":1357}],[],[{"OBJECTID":90698,"Unit_Nm":"City of Boulder City Parks","Pub_Access":"OA","MngNm_Desc":"City Land","MngTp_Desc":"Local Government","DesTp_Desc":"Local Park","GIS_Acres":1357}],[],[],[],[],[],[],[],[],[],[],[],[],[],[],[],[],[],[],[],[],[],[],[],[],[],[],[],[],[],[],[],[],[],[],[],[],[],[],[],[],[],[],[],[],[],[],[],[],[],[],[],[],[],[{"OBJECTID":90698,"Unit_Nm":"City of Boulder City Parks","Pub_Access":"OA","MngNm_Desc":"City Land","MngTp_Desc":"Local Government","DesTp_Desc":"Local Park","GIS_Acres":1357}],[],[],[],[],[],[],[],[],[],[],[],[],[],[],[],[],[{"OBJECTID":229588,"Unit_Nm":"Alvin New","Pub_Access":"OA","MngNm_Desc":"City Land","MngTp_Desc":"Local Government","DesTp_Desc":"Local Other or Unknown","GIS_Acres":20}],[],[],[],[],[],[{"OBJECTID":90698,"Unit_Nm":"City of Boulder City Parks","Pub_Access":"OA","MngNm_Desc":"City Land","MngTp_Desc":"Local Government","DesTp_Desc":"Local Park","GIS_Acres":1357}],[],[{"OBJECTID":90698,"Unit_Nm":"City of Boulder City Parks","Pub_Access":"OA","MngNm_Desc":"City Land","MngTp_Desc":"Local Government","DesTp_Desc":"Local Park","GIS_Acres":1357}],[{"OBJECTID":90698,"Unit_Nm":"City of Boulder City Parks","Pub_Access":"OA","MngNm_Desc":"City Land","MngTp_Desc":"Local Government","DesTp_Desc":"Local Park","GIS_Acres":1357}],[],[],[],[],[],[],[],[],[],[],[],[],[],[],[],[],[],[],[],[],[],[],[],[],[],[],[],[],[],[],[],[],[],[],[],[],[],[],[],[],[],[],[],[],[],[],[],[{"OBJECTID":153143,"Unit_Nm":"Greenleaf Park","Pub_Access":"OA","MngNm_Desc":"City Land","MngTp_Desc":"Local Government","DesTp_Desc":"Local Park","GIS_Acres":29}],[{"OBJECTID":153143,"Unit_Nm":"Greenleaf Park","Pub_Access":"OA","MngNm_Desc":"City Land","MngTp_Desc":"Local Government","DesTp_Desc":"Local Park","GIS_Acres":29}],[],[{"OBJECTID":153143,"Unit_Nm":"Greenleaf Park","Pub_Access":"OA","MngNm_Desc":"City Land","MngTp_Desc":"Local Government","DesTp_Desc":"Local Park","GIS_Acres":29}],[],[],[{"OBJECTID":153143,"Unit_Nm":"Greenleaf Park","Pub_Access":"OA","MngNm_Desc":"City Land","MngTp_Desc":"Local Government","DesTp_Desc":"Local Park","GIS_Acres":29}],[{"OBJECTID":153143,"Unit_Nm":"Greenleaf Park","Pub_Access":"OA","MngNm_Desc":"City Land","MngTp_Desc":"Local Government","DesTp_Desc":"Local Park","GIS_Acres":29}],[{"OBJECTID":153143,"Unit_Nm":"Greenleaf Park","Pub_Access":"OA","MngNm_Desc":"City Land","MngTp_Desc":"Local Government","DesTp_Desc":"Local Park","GIS_Acres":29}],[],[],[],[],[],[],[],[],[],[],[],[],[],[],[],[],[],[],[],[{"OBJECTID":37830,"Unit_Nm":"Boulder Memorial Hospital - Open Space","Pub_Access":"OA","MngNm_Desc":"City Land","MngTp_Desc":"Local Government","DesTp_Desc":"Local Other or Unknown","GIS_Acres":211}],[],[],[],[],[],[],[],[]]
