[{"key":"w07215_n04170","center":[-72.125,41.725],"units":[]},{"key":"w07210_n04170","center":[-72.075,41.725],"units":[]},{"key":"w07205_n04170","center":[-72.025,41.725],"units":[]},{"key":"w07215_n04175","center":[-72.125,41.775],"units":[]},{"key":"w07210_n04175","center":[-72.075,41.775],"units":[]},{"key":"w07205_n04175","center":[-72.025,41.775],"units":[]},{"key":"w07215_n04180","center":[-72.125,41.825],"units":[]},{"key":"w07210_n04180","center":[-72.075,41.825],"units":[]},{"key":"w07205_n04180","center":[-72.025,41.825],"units":[]}]
