[{"key":"w07320_n04260","center":[-73.175,42.625],"units":[{"OBJECTID":289479,"Unit_Nm":"Mount Greylock State Reservation","Pub_Access":"OA","MngNm_Desc":"Unknown","MngTp_Desc":"Unknown","DesTp_Desc":"State Park","GIS_Acres":12401}]},{"key":"w07315_n04260","center":[-73.125,42.625],"units":[],"samples":[[],[],[{"OBJECTID":259145,"Unit_Nm":"Greylock Glen","Pub_Access":"OA","MngNm_Desc":"Unknown","MngTp_Desc":"Unknown","DesTp_Desc":"State Other or Unknown","GIS_Acres":1070}],[],[]]},{"key":"w07310_n04260","center":[-73.075,42.625],"units":[{"OBJECTID":110153,"Unit_Nm":"Savoy Mountain State Forest","Pub_Access":"OA","MngNm_Desc":"Unknown","MngTp_Desc":"Unknown","DesTp_Desc":"State Resource Management Area","GIS_Acres":3425}],"samples":[[{"OBJECTID":110153,"Unit_Nm":"Savoy Mountain State Forest","Pub_Access":"OA","MngNm_Desc":"Unknown","MngTp_Desc":"Unknown","DesTp_Desc":"State Resource Management Area","GIS_Acres":3425}],[],[],[],[]]},{"key":"w07320_n04265","center":[-73.175,42.675],"units":[{"OBJECTID":289479,"Unit_Nm":"Mount Greylock State Reservation","Pub_Access":"OA","MngNm_Desc":"Unknown","MngTp_Desc":"Unknown","DesTp_Desc":"State Park","GIS_Acres":12401}],"samples":[[{"OBJECTID":289479,"Unit_Nm":"Mount Greylock State Reservation","Pub_Access":"OA","MngNm_Desc":"Unknown","MngTp_Desc":"Unknown","DesTp_Desc":"State Park","GIS_Acres":12401}],[],[],[{"OBJECTID":289479,"Unit_Nm":"Mount Greylock State Reservation","Pub_Access":"OA","MngNm_Desc":"Unknown","MngTp_Desc":"Unknown","DesTp_Desc":"State Park","GIS_Acres":12401}],[{"OBJECTID":289479,"Unit_Nm":"Mount Greylock State Reservation","Pub_Access":"OA","MngNm_Desc":"Unknown","MngTp_Desc":"Unknown","DesTp_Desc":"State Park","GIS_Acres":12401}]]},{"key":"w07315_n04265","center":[-73.125,42.675],"units":[],"samples":[[],[],[{"OBJECTID":50755,"Unit_Nm":"The Cascades","Pub_Access":"OA","MngNm_Desc":"Unknown","MngTp_Desc":"Unknown","DesTp_Desc":"Local Other or Unknown","GIS_Acres":39}],[],[]]},{"key":"w07310_n04265","center":[-73.075,42.675],"units":[{"OBJECTID":65736,"Unit_Nm":"Berkshire Natural Resource Council I CR","Pub_Access":"OA","MngNm_Desc":"State Park and Recreation","MngTp_Desc":"State","DesTp_Desc":"Conservation Easement","GIS_Acres":738}],"samples":[[{"OBJECTID":65736,"Unit_Nm":"Berkshire Natural Resource Council I CR","Pub_Access":"OA","MngNm_Desc":"State Park and Recreation","MngTp_Desc":"State","DesTp_Desc":"Conservation Easement","GIS_Acres":738}],[{"OBJECTID":65736,"Unit_Nm":"Berkshire Natural Resource Council I CR","Pub_Access":"OA","MngNm_Desc":"State Park and Recreation","MngTp_Desc":"State","DesTp_Desc":"Conservation Easement","GIS_Acres":738}],[],[{"OBJECTID":110153,"Unit_Nm":"Savoy Mountain State Forest","Pub_Access":"OA","MngNm_Desc":"Unknown","MngTp_Desc":"Unknown","DesTp_Desc":"State Resource Management Area","GIS_Acres":3425}],[]]},{"key":"w07320_n04270","center":[-73.175,42.725],"units":[{"OBJECTID":29789,"Unit_Nm":"Pine Cobble Preserve","Pub_Access":"OA","MngNm_Desc":"Unknown","MngTp_Desc":"Unknown","DesTp_Desc":"Private Conservation","GIS_Acres":209}],"samples":[[{"OBJECTID":29789,"Unit_Nm":"Pine Cobble Preserve","Pub_Access":"OA","MngNm_Desc":"Unknown","MngTp_Desc":"Unknown","DesTp_Desc":"Private Conservation","GIS_Acres":209}],[],[],[],[]]},{"key":"w07315_n04270","center":[-73.125,42.725],"units":[],"samples":[[],[],[{"OBJECTID":162330,"Unit_Nm":"Clarksburg State Forest","Pub_Access":"OA","MngNm_Desc":"Unknown","MngTp_Desc":"Unknown","DesTp_Desc":"State Resource Management Area","GIS_Acres":370}],[],[]]},{"key":"w07310_n04270","center":[-73.075,42.725],"units":[],"samples":[[],[],[{"OBJECTID":55723,"Unit_Nm":"Clarksburg State Park","Pub_Access":"OA","MngNm_Desc":"State Park and Recreation","MngTp_Desc":"State","DesTp_Desc":"State Park","GIS_Acres":375}],[{"OBJECTID":133687,"Unit_Nm":"Florida State Forest","Pub_Access":"OA","MngNm_Desc":"Unknown","MngTp_Desc":"Unknown","DesTp_Desc":"State Resource Management Area","GIS_Acres":987}],[]]}]
