[{"key":"w07740_n04005","center":[-77.375,40.075],"units":[],"samples":[[],[],[],[{"OBJECTID":54903,"Unit_Nm":"Michaux State Forest","Pub_Access":"OA","MngNm_Desc":"State Department of Natural Resources","MngTp_Desc":"State","DesTp_Desc":"State Resource Management Area","GIS_Acres":85087}],[{"OBJECTID":54903,"Unit_Nm":"Michaux State Forest","Pub_Access":"OA","MngNm_Desc":"State Department of Natural Resources","MngTp_Desc":"State","DesTp_Desc":"State Resource Management Area","GIS_Acres":85087}]]},{"key":"w07735_n04005","center":[-77.325,40.075],"units":[],"samples":[[],[],[],[],[{"OBJECTID":54903,"Unit_Nm":"Michaux State Forest","Pub_Access":"OA","MngNm_Desc":"State Department of Natural Resources","MngTp_Desc":"State","DesTp_Desc":"State Resource Management Area","GIS_Acres":85087}]]},{"key":"w07730_n04005","center":[-77.275,40.075],"units":[{"OBJECTID":54903,"Unit_Nm":"Michaux State Forest","Pub_Access":"OA","MngNm_Desc":"State Department of Natural Resources","MngTp_Desc":"State","DesTp_Desc":"State Resource Management Area","GIS_Acres":85087}],"samples":[[{"OBJECTID":54903,"Unit_Nm":"Michaux State Forest","Pub_Access":"OA","MngNm_Desc":"State Department of Natural Resources","MngTp_Desc":"State","DesTp_Desc":"State Resource Management Area","GIS_Acres":85087}],[],[],[{"OBJECTID":54903,"Unit_Nm":"Michaux State Forest","Pub_Access":"OA","MngNm_Desc":"State Department of Natural Resources","MngTp_Desc":"State","DesTp_Desc":"State Resource Management Area","GIS_Acres":85087}],[{"OBJECTID":54903,"Unit_Nm":"Michaux State Forest","Pub_Access":"OA","MngNm_Desc":"State Department of Natural Resources","MngTp_Desc":"State","DesTp_Desc":"State Resource Management Area","GIS_Acres":85087}]]},{"key":"w07740_n04010","center":[-77.375,40.125],"units":[]},{"key":"w07735_n04010","center":[-77.325,40.125],"units":[]},{"key":"w07730_n04010","center":[-77.275,40.125],"units":[]},{"key":"w07740_n04015","center":[-77.375,40.175],"units":[]},{"key":"w07735_n04015","center":[-77.325,40.175],"units":[]},{"key":"w07730_n04015","center":[-77.275,40.175],"units":[]}]
