[{"key":"w08025_n02565","center":[-80.225,25.675],"units":[]},{"key":"w08020_n02565","center":[-80.175,25.675],"units":[]},{"key":"w08015_n02565","center":[-80.125,25.675],"units":[]},{"key":"w08025_n02570","center":[-80.225,25.725],"units":[]},{"key":"w08020_n02570","center":[-80.175,25.725],"units":[]},{"key":"w08015_n02570","center":[-80.125,25.725],"units":[]},{"key":"w08025_n02575","center":[-80.225,25.775],"units":[]},{"key":"w08020_n02575","center":[-80.175,25.775],"units":[]},{"key":"w08015_n02575","center":[-80.125,25.775],"units":[]}]
