[{"key":"w08280_n03465","center":[-82.775,34.675],"units":[]},{"key":"w08275_n03465","center":[-82.725,34.675],"units":[]},{"key":"w08270_n03465","center":[-82.675,34.675],"units":[]},{"key":"w08280_n03470","center":[-82.775,34.725],"units":[]},{"key":"w08275_n03470","center":[-82.725,34.725],"units":[]},{"key":"w08270_n03470","center":[-82.675,34.725],"units":[]},{"key":"w08280_n03475","center":[-82.775,34.775],"units":[]},{"key":"w08275_n03475","center":[-82.725,34.775],"units":[]},{"key":"w08270_n03475","center":[-82.675,34.775],"units":[]}]
