[{"key":"w08370_n03270","center":[-83.675,32.725],"units":[]},{"key":"w08365_n03270","center":[-83.625,32.725],"units":[]},{"key":"w08360_n03270","center":[-83.575,32.725],"units":[{"OBJECTID":128530,"Unit_Nm":"Bond Swamp National Wildlife Refuge","Pub_Access":"RA","MngNm_Desc":"U.S. Fish and Wildlife Service","MngTp_Desc":"Federal","DesTp_Desc":"National Wildlife Refuge","GIS_Acres":7671}]},{"key":"w08370_n03275","center":[-83.675,32.775],"units":[]},{"key":"w08365_n03275","center":[-83.625,32.775],"units":[]},{"key":"w08360_n03275","center":[-83.575,32.775],"units":[]},{"key":"w08370_n03280","center":[-83.675,32.825],"units":[]},{"key":"w08365_n03280","center":[-83.625,32.825],"units":[]},{"key":"w08360_n03280","center":[-83.575,32.825],"units":[{"OBJECTID":93977,"Unit_Nm":"Ocmulgee Mounds National Historical Park","Pub_Access":"RA","MngNm_Desc":"National Park Service","MngTp_Desc":"Federal","DesTp_Desc":"Historic or Cultural Area","GIS_Acres":1748}]}]
