[{"key":"w08430_n03600","center":[-84.275,36.025],"units":[{"OBJECTID":7194,"Unit_Nm":"City Of Oak Ridge","Pub_Access":"OA","MngNm_Desc":"City Land","MngTp_Desc":"Local Government","DesTp_Desc":"Local Other or Unknown","GIS_Acres":288}]},{"key":"w08425_n03600","center":[-84.225,36.025],"units":[]},{"key":"w08420_n03600","center":[-84.175,36.025],"units":[]},{"key":"w08430_n03605","center":[-84.275,36.075],"units":[]},{"key":"w08425_n03605","center":[-84.225,36.075],"units":[]},{"key":"w08420_n03605","center":[-84.175,36.075],"units":[]},{"key":"w08430_n03610","center":[-84.275,36.125],"units":[]},{"key":"w08425_n03610","center":[-84.225,36.125],"units":[]},{"key":"w08420_n03610","center":[-84.175,36.125],"units":[]}]
