[{"key":"w08520_n04290","center":[-85.175,42.925],"units":[]},{"key":"w08515_n04290","center":[-85.125,42.925],"units":[]},{"key":"w08510_n04290","center":[-85.075,42.925],"units":[]},{"key":"w08520_n04295","center":[-85.175,42.975],"units":[]},{"key":"w08515_n04295","center":[-85.125,42.975],"units":[]},{"key":"w08510_n04295","center":[-85.075,42.975],"units":[{"OBJECTID":298842,"Unit_Nm":"Ionia Free Fairgrounds","Pub_Access":"RA","MngNm_Desc":"County Land","MngTp_Desc":"Local Government","DesTp_Desc":"Local Recreation Area","GIS_Acres":144}]},{"key":"w08520_n04300","center":[-85.175,43.025],"units":[]},{"key":"w08515_n04300","center":[-85.125,43.025],"units":[]},{"key":"w08510_n04300","center":[-85.075,43.025],"units":[]}]
