[{"key":"w08790_n04170","center":[-87.875,41.725],"units":[{"OBJECTID":296647,"Unit_Nm":"Willow Springs Woods","Pub_Access":"OA","MngNm_Desc":"Regional Agency Land","MngTp_Desc":"Regional Agency Special District","DesTp_Desc":"Unknown","GIS_Acres":421}]},{"key":"w08785_n04170","center":[-87.825,41.725],"units":[]},{"key":"w08780_n04170","center":[-87.775,41.725],"units":[]},{"key":"w08790_n04175","center":[-87.875,41.775],"units":[]},{"key":"w08785_n04175","center":[-87.825,41.775],"units":[]},{"key":"w08780_n04175","center":[-87.775,41.775],"units":[]},{"key":"w08790_n04180","center":[-87.875,41.825],"units":[]},{"key":"w08785_n04180","center":[-87.825,41.825],"units":[]},{"key":"w08780_n04180","center":[-87.775,41.825],"units":[]}]
