[{"key":"w08955_n04305","center":[-89.525,43.075],"units":[]},{"key":"w08950_n04305","center":[-89.475,43.075],"units":[]},{"key":"w08945_n04305","center":[-89.425,43.075],"units":[]},{"key":"w08955_n04310","center":[-89.525,43.125],"units":[]},{"key":"w08950_n04310","center":[-89.475,43.125],"units":[]},{"key":"w08945_n04310","center":[-89.425,43.125],"units":[]},{"key":"w08955_n04315","center":[-89.525,43.175],"units":[]},{"key":"w08950_n04315","center":[-89.475,43.175],"units":[]},{"key":"w08945_n04315","center":[-89.425,43.175],"units":[]}]
