[{"key":"w09075_n04155","center":[-90.725,41.575],"units":[]},{"key":"w09070_n04155","center":[-90.675,41.575],"units":[]},{"key":"w09065_n04155","center":[-90.625,41.575],"units":[]},{"key":"w09075_n04160","center":[-90.725,41.625],"units":[]},{"key":"w09070_n04160","center":[-90.675,41.625],"units":[]},{"key":"w09065_n04160","center":[-90.625,41.625],"units":[]},{"key":"w09075_n04165","center":[-90.725,41.675],"units":[]},{"key":"w09070_n04165","center":[-90.675,41.675],"units":[]},{"key":"w09065_n04165","center":[-90.625,41.675],"units":[]}]
