[{"key":"w11640_n04365","center":[-116.375,43.675],"units":[],"samples":[[],[],[{"OBJECTID":99667,"Unit_Nm":"Eagle Island State Park","Pub_Access":"OA","MngNm_Desc":"State Park and Recreation","MngTp_Desc":"State","DesTp_Desc":"State Park","GIS_Acres":531}],[],[]]},{"key":"w11635_n04365","center":[-116.325,43.675],"units":[]},{"key":"w11630_n04365","center":[-116.275,43.675],"units":[],"samples":[[],[{"OBJECTID":271432,"Unit_Nm":"Pursley Site","Pub_Access":"OA","MngNm_Desc":"City Land","MngTp_Desc":"Local Government","DesTp_Desc":"Local Park","GIS_Acres":29}],[],[],[]]},{"key":"w11640_n04370","center":[-116.375,43.725],"units":[]},{"key":"w11635_n04370","center":[-116.325,43.725],"units":[],"samples":[[],[],[],[{"OBJECTID":20290,"Unit_Nm":"Eagle Ada Sports Complex","Pub_Access":"OA","MngNm_Desc":"City Land","MngTp_Desc":"Local Government","DesTp_Desc":"Local Park","GIS_Acres":102}],[]]},{"key":"w11630_n04370","center":[-116.275,43.725],"units":[]},{"key":"w11640_n04375","center":[-116.375,43.775],"units":[]},{"key":"w11635_n04375","center":[-116.325,43.775],"units":[]},{"key":"w11630_n04375","center":[-116.275,43.775],"units":[]}]
