[{"key":"w11955_n03645","center":[-119.525,36.475],"units":[]},{"key":"w11950_n03645","center":[-119.475,36.475],"units":[]},{"key":"w11945_n03645","center":[-119.425,36.475],"units":[]},{"key":"w11955_n03650","center":[-119.525,36.525],"units":[]},{"key":"w11950_n03650","center":[-119.475,36.525],"units":[]},{"key":"w11945_n03650","center":[-119.425,36.525],"units":[]},{"key":"w11955_n03655","center":[-119.525,36.575],"units":[]},{"key":"w11950_n03655","center":[-119.475,36.575],"units":[]},{"key":"w11945_n03655","center":[-119.425,36.575],"units":[]}]
