[{"key":"w12045_n04845","center":[-120.425,48.475],"units":[{"OBJECTID":125977,"Unit_Nm":"Lake Chelan-Sawtooth Wilderness","Pub_Access":"RA","MngNm_Desc":"Forest Service","MngTp_Desc":"Federal","DesTp_Desc":"Wilderness Area","GIS_Acres":153119}],"samples":[[{"OBJECTID":125977,"Unit_Nm":"Lake Chelan-Sawtooth Wilderness","Pub_Access":"RA","MngNm_Desc":"Forest Service","MngTp_Desc":"Federal","DesTp_Desc":"Wilderness Area","GIS_Acres":153119}],[{"OBJECTID":125977,"Unit_Nm":"Lake Chelan-Sawtooth Wilderness","Pub_Access":"RA","MngNm_Desc":"Forest Service","MngTp_Desc":"Federal","DesTp_Desc":"Wilderness Area","GIS_Acres":153119}],[{"OBJECTID":125977,"Unit_Nm":"Lake Chelan-Sawtooth Wilderness","Pub_Access":"RA","MngNm_Desc":"Forest Service","MngTp_Desc":"Federal","DesTp_Desc":"Wilderness Area","GIS_Acres":153119}],[{"OBJECTID":76679,"Unit_Nm":"Sawtooth Roadless Area","Pub_Access":"OA","MngNm_Desc":"Forest Service","MngTp_Desc":"Federal","DesTp_Desc":"Inventoried Roadless Area","GIS_Acres":102259}],[{"OBJECTID":125977,"Unit_Nm":"Lake Chelan-Sawtooth Wilderness","Pub_Access":"RA","MngNm_Desc":"Forest Service","MngTp_Desc":"Federal","DesTp_Desc":"Wilderness Area","GIS_Acres":153119}]]},{"key":"w12040_n04845","center":[-120.375,48.475],"units":[{"OBJECTID":125977,"Unit_Nm":"Lake Chelan-Sawtooth Wilderness","Pub_Access":"RA","MngNm_Desc":"Forest Service","MngTp_Desc":"Federal","DesTp_Desc":"Wilderness Area","GIS_Acres":153119}],"samples":[[{"OBJECTID":125977,"Unit_Nm":"Lake Chelan-Sawtooth Wilderness","Pub_Access":"RA","MngNm_Desc":"Forest Service","MngTp_Desc":"Federal","DesTp_Desc":"Wilderness Area","GIS_Acres":153119}],[{"OBJECTID":125977,"Unit_Nm":"Lake Chelan-Sawtooth Wilderness","Pub_Access":"RA","MngNm_Desc":"Forest Service","MngTp_Desc":"Federal","DesTp_Desc":"Wilderness Area","GIS_Acres":153119}],[{"OBJECTID":125977,"Unit_Nm":"Lake Chelan-Sawtooth Wilderness","Pub_Access":"RA","MngNm_Desc":"Forest Service","MngTp_Desc":"Federal","DesTp_Desc":"Wilderness Area","GIS_Acres":153119}],[{"OBJECTID":125977,"Unit_Nm":"Lake Chelan-Sawtooth Wilderness","Pub_Access":"RA","MngNm_Desc":"Forest Service","MngTp_Desc":"Federal","DesTp_Desc":"Wilderness Area","GIS_Acres":153119}],[{"OBJECTID":289795,"Unit_Nm":"Okanogan National Forest","Pub_Access":"OA","MngNm_Desc":"Forest Service","MngTp_Desc":"Federal","DesTp_Desc":"National Forest","GIS_Acres":639574}]]},{"key":"w12035_n04845","center":[-120.325,48.475],"units":[{"OBJECTID":125977,"Unit_Nm":"Lake Chelan-Sawtooth Wilderness","Pub_Access":"RA","MngNm_Desc":"Forest Service","MngTp_Desc":"Federal","DesTp_Desc":"Wilderness Area","GIS_Acres":153119}],"samples":[[{"OBJECTID":125977,"Unit_Nm":"Lake Chelan-Sawtooth Wilderness","Pub_Access":"RA","MngNm_Desc":"Forest Service","MngTp_Desc":"Federal","DesTp_Desc":"Wilderness Area","GIS_Acres":153119}],[{"OBJECTID":125977,"Unit_Nm":"Lake Chelan-Sawtooth Wilderness","Pub_Access":"RA","MngNm_Desc":"Forest Service","MngTp_Desc":"Federal","DesTp_Desc":"Wilderness Area","GIS_Acres":153119}],[{"OBJECTID":125977,"Unit_Nm":"Lake Chelan-Sawtooth Wilderness","Pub_Access":"RA","MngNm_Desc":"Forest Service","MngTp_Desc":"Federal","DesTp_Desc":"Wilderness Area","GIS_Acres":153119}],[{"OBJECTID":76679,"Unit_Nm":"Sawtooth Roadless Area","Pub_Access":"OA","MngNm_Desc":"Forest Service","MngTp_Desc":"Federal","DesTp_Desc":"Inventoried Roadless Area","GIS_Acres":102259}],[{"OBJECTID":76679,"Unit_Nm":"Sawtooth Roadless Area","Pub_Access":"OA","MngNm_Desc":"Forest Service","MngTp_Desc":"Federal","DesTp_Desc":"Inventoried Roadless Area","GIS_Acres":102259}]]},{"key":"w12045_n04850","center":[-120.425,48.525],"units":[{"OBJECTID":125977,"Unit_Nm":"Lake Chelan-Sawtooth Wilderness","Pub_Access":"RA","MngNm_Desc":"Forest Service","MngTp_Desc":"Federal","DesTp_Desc":"Wilderness Area","GIS_Acres":153119}],"samples":[[{"OBJECTID":125977,"Unit_Nm":"Lake Chelan-Sawtooth Wilderness","Pub_Access":"RA","MngNm_Desc":"Forest Service","MngTp_Desc":"Federal","DesTp_Desc":"Wilderness Area","GIS_Acres":153119}],[{"OBJECTID":76679,"Unit_Nm":"Sawtooth Roadless Area","Pub_Access":"OA","MngNm_Desc":"Forest Service","MngTp_Desc":"Federal","DesTp_Desc":"Inventoried Roadless Area","GIS_Acres":102259}],[{"OBJECTID":76679,"Unit_Nm":"Sawtooth Roadless Area","Pub_Access":"OA","MngNm_Desc":"Forest Service","MngTp_Desc":"Federal","DesTp_Desc":"Inventoried Roadless Area","GIS_Acres":102259}],[{"OBJECTID":125977,"Unit_Nm":"Lake Chelan-Sawtooth Wilderness","Pub_Access":"RA","MngNm_Desc":"Forest Service","MngTp_Desc":"Federal","DesTp_Desc":"Wilderness Area","GIS_Acres":153119}],[{"OBJECTID":125977,"Unit_Nm":"Lake Chelan-Sawtooth Wilderness","Pub_Access":"RA","MngNm_Desc":"Forest Service","MngTp_Desc":"Federal","DesTp_Desc":"Wilderness Area","GIS_Acres":153119}]]},{"key":"w12040_n04850","center":[-120.375,48.525],"units":[{"OBJECTID":76679,"Unit_Nm":"Sawtooth Roadless Area","Pub_Access":"OA","MngNm_Desc":"Forest Service","MngTp_Desc":"Federal","DesTp_Desc":"Inventoried Roadless Area","GIS_Acres":102259}],"samples":[[{"OBJECTID":76679,"Unit_Nm":"Sawtooth Roadless Area","Pub_Access":"OA","MngNm_Desc":"Forest Service","MngTp_Desc":"Federal","DesTp_Desc":"Inventoried Roadless Area","GIS_Acres":102259}],[{"OBJECTID":76679,"Unit_Nm":"Sawtooth Roadless Area","Pub_Access":"OA","MngNm_Desc":"Forest Service","MngTp_Desc":"Federal","DesTp_Desc":"Inventoried Roadless Area","GIS_Acres":102259}],[{"OBJECTID":76679,"Unit_Nm":"Sawtooth Roadless Area","Pub_Access":"OA","MngNm_Desc":"Forest Service","MngTp_Desc":"Federal","DesTp_Desc":"Inventoried Roadless Area","GIS_Acres":102259}],[{"OBJECTID":76679,"Unit_Nm":"Sawtooth Roadless Area","Pub_Access":"OA","MngNm_Desc":"Forest Service","MngTp_Desc":"Federal","DesTp_Desc":"Inventoried Roadless Area","GIS_Acres":102259}],[{"OBJECTID":125977,"Unit_Nm":"Lake Chelan-Sawtooth Wilderness","Pub_Access":"RA","MngNm_Desc":"Forest Service","MngTp_Desc":"Federal","DesTp_Desc":"Wilderness Area","GIS_Acres":153119}]]},{"key":"w12035_n04850","center":[-120.325,48.525],"units":[{"OBJECTID":289795,"Unit_Nm":"Okanogan National Forest","Pub_Access":"OA","MngNm_Desc":"Forest Service","MngTp_Desc":"Federal","DesTp_Desc":"National Forest","GIS_Acres":639574}],"samples":[[{"OBJECTID":289795,"Unit_Nm":"Okanogan National Forest","Pub_Access":"OA","MngNm_Desc":"Forest Service","MngTp_Desc":"Federal","DesTp_Desc":"National Forest","GIS_Acres":639574}],[{"OBJECTID":289795,"Unit_Nm":"Okanogan National Forest","Pub_Access":"OA","MngNm_Desc":"Forest Service","MngTp_Desc":"Federal","DesTp_Desc":"National Forest","GIS_Acres":639574}],[],[{"OBJECTID":289795,"Unit_Nm":"Okanogan National Forest","Pub_Access":"OA","MngNm_Desc":"Forest Service","MngTp_Desc":"Federal","DesTp_Desc":"National Forest","GIS_Acres":639574}],[{"OBJECTID":76679,"Unit_Nm":"Sawtooth Roadless Area","Pub_Access":"OA","MngNm_Desc":"Forest Service","MngTp_Desc":"Federal","DesTp_Desc":"Inventoried Roadless Area","GIS_Acres":102259}]]},{"key":"w12045_n04855","center":[-120.425,48.575],"units":[{"OBJECTID":76679,"Unit_Nm":"Sawtooth Roadless Area","Pub_Access":"OA","MngNm_Desc":"Forest Service","MngTp_Desc":"Federal","DesTp_Desc":"Inventoried Roadless Area","GIS_Acres":102259}],"samples":[[{"OBJECTID":76679,"Unit_Nm":"Sawtooth Roadless Area","Pub_Access":"OA","MngNm_Desc":"Forest Service","MngTp_Desc":"Federal","DesTp_Desc":"Inventoried Roadless Area","GIS_Acres":102259}],[],[{"OBJECTID":289795,"Unit_Nm":"Okanogan National Forest","Pub_Access":"OA","MngNm_Desc":"Forest Service","MngTp_Desc":"Federal","DesTp_Desc":"National Forest","GIS_Acres":639574}],[{"OBJECTID":76679,"Unit_Nm":"Sawtooth Roadless Area","Pub_Access":"OA","MngNm_Desc":"Forest Service","MngTp_Desc":"Federal","DesTp_Desc":"Inventoried Roadless Area","GIS_Acres":102259}],[{"OBJECTID":76679,"Unit_Nm":"Sawtooth Roadless Area","Pub_Access":"OA","MngNm_Desc":"Forest Service","MngTp_Desc":"Federal","DesTp_Desc":"Inventoried Roadless Area","GIS_Acres":102259}]]},{"key":"w12040_n04855","center":[-120.375,48.575],"units":[],"samples":[[],[{"OBJECTID":289795,"Unit_Nm":"Okanogan National Forest","Pub_Access":"OA","MngNm_Desc":"Forest Service","MngTp_Desc":"Federal","DesTp_Desc":"National Forest","GIS_Acres":639574}],[],[],[{"OBJECTID":289795,"Unit_Nm":"Okanogan National Forest","Pub_Access":"OA","MngNm_Desc":"Forest Service","MngTp_Desc":"Federal","DesTp_Desc":"National Forest","GIS_Acres":639574}]]},{"key":"w12035_n04855","center":[-120.325,48.575],"units":[{"OBJECTID":289795,"Unit_Nm":"Okanogan National Forest","Pub_Access":"OA","MngNm_Desc":"Forest Service","MngTp_Desc":"Federal","DesTp_Desc":"National Forest","GIS_Acres":639574}],"samples":[[{"OBJECTID":289795,"Unit_Nm":"Okanogan National Forest","Pub_Access":"OA","MngNm_Desc":"Forest Service","MngTp_Desc":"Federal","DesTp_Desc":"National Forest","GIS_Acres":639574}],[{"OBJECTID":289795,"Unit_Nm":"Okanogan National Forest","Pub_Access":"OA","MngNm_Desc":"Forest Service","MngTp_Desc":"Federal","DesTp_Desc":"National Forest","GIS_Acres":639574}],[{"OBJECTID":289795,"Unit_Nm":"Okanogan National Forest","Pub_Access":"OA","MngNm_Desc":"Forest Service","MngTp_Desc":"Federal","DesTp_Desc":"National Forest","GIS_Acres":639574}],[{"OBJECTID":289795,"Unit_Nm":"Okanogan National Forest","Pub_Access":"OA","MngNm_Desc":"Forest Service","MngTp_Desc":"Federal","DesTp_Desc":"National Forest","GIS_Acres":639574}],[]]}]
