[{"key":"w12180_n04815","center":[-121.775,48.175],"units":[{"OBJECTID":26949,"Unit_Nm":"Boulder River Wilderness","Pub_Access":"RA","MngNm_Desc":"Forest Service","MngTp_Desc":"Federal","DesTp_Desc":"Wilderness Area","GIS_Acres":49249}]},{"key":"w12175_n04815","center":[-121.725,48.175],"units":[{"OBJECTID":26949,"Unit_Nm":"Boulder River Wilderness","Pub_Access":"RA","MngNm_Desc":"Forest Service","MngTp_Desc":"Federal","DesTp_Desc":"Wilderness Area","GIS_Acres":49249}]},{"key":"w12170_n04815","center":[-121.675,48.175],"units":[{"OBJECTID":26949,"Unit_Nm":"Boulder River Wilderness","Pub_Access":"RA","MngNm_Desc":"Forest Service","MngTp_Desc":"Federal","DesTp_Desc":"Wilderness Area","GIS_Acres":49249}]},{"key":"w12180_n04820","center":[-121.775,48.225],"units":[{"OBJECTID":26949,"Unit_Nm":"Boulder River Wilderness","Pub_Access":"RA","MngNm_Desc":"Forest Service","MngTp_Desc":"Federal","DesTp_Desc":"Wilderness Area","GIS_Acres":49249}]},{"key":"w12175_n04820","center":[-121.725,48.225],"units":[{"OBJECTID":258306,"Unit_Nm":"Boulder River Roadless Area","Pub_Access":"OA","MngNm_Desc":"Forest Service","MngTp_Desc":"Federal","DesTp_Desc":"Inventoried Roadless Area","GIS_Acres":29733}]},{"key":"w12170_n04820","center":[-121.675,48.225],"units":[{"OBJECTID":26949,"Unit_Nm":"Boulder River Wilderness","Pub_Access":"RA","MngNm_Desc":"Forest Service","MngTp_Desc":"Federal","DesTp_Desc":"Wilderness Area","GIS_Acres":49249}]},{"key":"w12180_n04825","center":[-121.775,48.275],"units":[]},{"key":"w12175_n04825","center":[-121.725,48.275],"units":[]},{"key":"w12170_n04825","center":[-121.675,48.275],"units":[]}]
