[{"key":"w12255_n03975","center":[-122.525,39.775],"units":[]},{"key":"w12250_n03975","center":[-122.475,39.775],"units":[]},{"key":"w12245_n03975","center":[-122.425,39.775],"units":[]},{"key":"w12255_n03980","center":[-122.525,39.825],"units":[]},{"key":"w12250_n03980","center":[-122.475,39.825],"units":[]},{"key":"w12245_n03980","center":[-122.425,39.825],"units":[]},{"key":"w12255_n03985","center":[-122.525,39.875],"units":[]},{"key":"w12250_n03985","center":[-122.475,39.875],"units":[]},{"key":"w12245_n03985","center":[-122.425,39.875],"units":[]}]
